Workbook
Name UPDATE: 'Data Sheet'!$E$1

Sheet Profit & Loss
A1: ='Data Sheet'!B1 -> TATA MOTORS LTD | H1: =UPDATE | M1: SCREENER.IN
A3: Narration | B3: ='Data Sheet'!B16 -> 42460 | C3: ='Data Sheet'!C16 -> 42825 | D3: ='Data Sheet'!D16 -> 43190 | E3: ='Data Sheet'!E16 -> 43555 | F3: ='Data Sheet'!F16 -> 43921 | G3: ='Data Sheet'!G16 -> 44286 | H3: ='Data Sheet'!H16 -> 44651 | I3: ='Data Sheet'!I16 -> 45016 | ... K3: ='Data Sheet'!K16 -> 45747 | L3: Trailing | M3: Best Case | N3: Worst Case
A4: Sales | B4: ='Data Sheet'!B17 -> 273045.6 | C4: ='Data Sheet'!C17 -> 269692.51 | D4: ='Data Sheet'!D17 -> 291550.48 | E4: ='Data Sheet'!E17 -> 301938.4 | F4: ='Data Sheet'!F17 -> 261067.97 | G4: ='Data Sheet'!G17 -> 249794.75 | H4: ='Data Sheet'!H17 -> 278453.62 | I4: ='Data Sheet'!I17 -> 345966.97 | ... K4: ='Data Sheet'!K17 -> 439695 | L4: =SUM(Quarters!H4:K4) -> 441609 | M4: =$K4+M23*K4 -> 512017.04 | N4: =$K4+N23*L4 -> 445473.35
A5: Expenses | B5: =SUM('Data Sheet'!B18,'Data Sheet'!B20:B24, -1*'Data Sheet'!B19) -> 234650.35 | C5: =SUM('Data Sheet'!C18,'Data Sheet'!C20:C24, -1*'Data Sheet'!C19) -> 240103.82 | D5: =SUM('Data Sheet'!D18,'Data Sheet'!D20:D24, -1*'Data Sheet'!D19) -> 260092.8 | E5: =SUM('Data Sheet'!E18,'Data Sheet'!E20:E24, -1*'Data Sheet'!E19) -> 277274.07 | F5: =SUM('Data Sheet'!F18,'Data Sheet'!F20:F24, -1*'Data Sheet'!F19) -> 243080.9 | G5: =SUM('Data Sheet'!G18,'Data Sheet'!G20:G24, -1*'Data Sheet'!G19) -> 217507.32 | H5: =SUM('Data Sheet'!H18,'Data Sheet'!H20:H24, -1*'Data Sheet'!H19) -> 253733.53 | I5: =SUM('Data Sheet'!I18,'Data Sheet'!I20:I24, -1*'Data Sheet'!I19) -> 314151.17 | ... K5: =SUM('Data Sheet'!K18,'Data Sheet'!K20:K24, -1*'Data Sheet'!K19) -> 384479 | L5: =SUM(Quarters!H5:K5) -> 384424 | M5: =M4-M6 -> 445714.73 | N5: =N4-N6 -> 398338.79
A6: Operating Profit | B6: =B4-B5 -> 38395.25 | C6: =C4-C5 -> 29588.69 | D6: =D4-D5 -> 31457.68 | E6: =E4-E5 -> 24664.33 | F6: =F4-F5 -> 17987.07 | G6: =G4-G5 -> 32287.43 | H6: =H4-H5 -> 24720.09 | I6: =I4-I5 -> 31815.8 | ... K6: =K4-K5 -> 55216 | L6: =SUM(Quarters!H6:K6) -> 57185 | M6: =M4*M24 -> 66302.304 | N6: =N4*N24 -> 47134.558
A7: Other Income | B7: ='Data Sheet'!B25 -> -2669.62 | C7: ='Data Sheet'!C25 -> 1869.1 | D7: ='Data Sheet'!D25 -> 5932.73 | E7: ='Data Sheet'!E25 -> -26686.25 | F7: ='Data Sheet'!F25 -> 101.71 | G7: ='Data Sheet'!G25 -> -11117.83 | H7: ='Data Sheet'!H25 -> 2424.05 | I7: ='Data Sheet'!I25 -> 6663.97 | ... K7: ='Data Sheet'!K25 -> 11774 | L7: =SUM(Quarters!H7:K7) -> 6151 | M7: 0 | N7: 0
A8: Depreciation | B8: ='Data Sheet'!B26 -> 16710.78 | C8: ='Data Sheet'!C26 -> 17904.99 | D8: ='Data Sheet'!D26 -> 21553.59 | E8: ='Data Sheet'!E26 -> 23590.63 | F8: ='Data Sheet'!F26 -> 21425.43 | G8: ='Data Sheet'!G26 -> 23546.71 | H8: ='Data Sheet'!H26 -> 24835.69 | I8: ='Data Sheet'!I26 -> 24860.36 | ... K8: ='Data Sheet'!K26 -> 23256 | L8: =SUM(Quarters!H8:K8) -> 23273 | M8: =+$L8 -> 23273 | N8: =+$L8 -> 23273
A9: Interest | B9: ='Data Sheet'!B27 -> 4889.08 | C9: ='Data Sheet'!C27 -> 4238.01 | D9: ='Data Sheet'!D27 -> 4681.79 | E9: ='Data Sheet'!E27 -> 5758.6 | F9: ='Data Sheet'!F27 -> 7243.33 | G9: ='Data Sheet'!G27 -> 8097.17 | H9: ='Data Sheet'!H27 -> 9311.86 | I9: ='Data Sheet'!I27 -> 10225.48 | ... K9: ='Data Sheet'!K27 -> 5083 | L9: =SUM(Quarters!H9:K9) -> 6317 | M9: =+$L9 -> 6317 | N9: =+$L9 -> 6317
A10: Profit before tax | B10: ='Data Sheet'!B28 -> 14125.77 | C10: ='Data Sheet'!C28 -> 9314.79 | D10: ='Data Sheet'!D28 -> 11155.03 | E10: ='Data Sheet'!E28 -> -31371.15 | F10: ='Data Sheet'!F28 -> -10579.98 | G10: ='Data Sheet'!G28 -> -10474.28 | H10: ='Data Sheet'!H28 -> -7003.41 | I10: ='Data Sheet'!I28 -> 3393.93 | ... K10: ='Data Sheet'!K28 -> 38651 | L10: =SUM(Quarters!H10:K10) -> 33746 | M10: =M6+M7-SUM(M8:M9) -> 36712.304 | N10: =N6+N7-SUM(N8:N9) -> 17544.558
A11: Tax | B11: ='Data Sheet'!B29 -> 3025.05 | C11: ='Data Sheet'!C29 -> 3251.23 | D11: ='Data Sheet'!D29 -> 4341.93 | E11: ='Data Sheet'!E29 -> -2437.45 | F11: ='Data Sheet'!F29 -> 395.25 | G11: ='Data Sheet'!G29 -> 2541.86 | H11: ='Data Sheet'!H29 -> 4231.29 | I11: ='Data Sheet'!I29 -> 704.06 | ... K11: ='Data Sheet'!K29 -> 10502 | L11: =SUM(Quarters!H11:K11) -> 10563 | M11: =IF($L10>0,$L11/$L10,0) -> 0.31301488 | N11: =IF($L10>0,$L11/$L10,0) -> 0.31301488
A12: Net profit | B12: ='Data Sheet'!B30 -> 11579.31 | C12: ='Data Sheet'!C30 -> 7454.36 | D12: ='Data Sheet'!D30 -> 8988.91 | E12: ='Data Sheet'!E30 -> -28826.23 | F12: ='Data Sheet'!F30 -> -12070.85 | G12: ='Data Sheet'!G30 -> -13451.39 | H12: ='Data Sheet'!H30 -> -11441.47 | I12: ='Data Sheet'!I30 -> 2414.29 | ... K12: ='Data Sheet'!K30 -> 27830 | L12: =SUM(Quarters!H12:K12) -> 22785 | M12: =M10-M11*M10 -> 25220.807 | N12: =N10-N11*N10 -> 12052.85
A13: EPS | B13: =IF('Data Sheet'!B93>0,B12/'Data Sheet'!B93,0) -> 40.105673 | C13: =IF('Data Sheet'!C93>0,C12/'Data Sheet'!C93,0) -> 25.817754 | D13: =IF('Data Sheet'!D93>0,D12/'Data Sheet'!D93,0) -> 31.132581 | E13: =IF('Data Sheet'!E93>0,E12/'Data Sheet'!E93,0) -> -99.838015 | F13: =IF('Data Sheet'!F93>0,F12/'Data Sheet'!F93,0) -> -39.076886 | G13: =IF('Data Sheet'!G93>0,G12/'Data Sheet'!G93,0) -> -40.512574 | H13: =IF('Data Sheet'!H93>0,H12/'Data Sheet'!H93,0) -> -34.454994 | I13: =IF('Data Sheet'!I93>0,I12/'Data Sheet'!I93,0) -> 7.2691115 | ... K13: =IF('Data Sheet'!K93>0,K12/'Data Sheet'!K93,0) -> 75.598294 | L13: =IF('Data Sheet'!$B6>0,'Profit & Loss'!L12/'Data Sheet'!$B6,0) -> 61.891168 | M13: =IF('Data Sheet'!$B6>0,'Profit & Loss'!M12/'Data Sheet'!$B6,0) -> 68.507579 | N13: =IF('Data Sheet'!$B6>0,'Profit & Loss'!N12/'Data Sheet'!$B6,0) -> 32.739302
A14: Price to earning | B14: =IF(B15>0,B15/B13,"") -> 9.639534 | C14: =IF(C15>0,C15/C13,"") -> 18.043785 | D14: =IF(D15>0,D15/D13,"") -> 10.498648 | E14: =IF(E15>0,E15/E13,"") -> -1.7453272 | F14: =IF(F15>0,F15/F13,"") -> -1.8182104 | G14: =IF(G15>0,G15/G13,"") -> -7.449539 | H14: =IF(H15>0,H15/H13,"") -> -12.588886 | I14: =IF(I15>0,I15/I13,"") -> 57.888781 | ... K14: =IF(K15>0,K15/K13,"") -> 8.9214976 | L14: =IF(L13>0,L15/L13,0) -> 10.862616 | M14: =M25 -> 22.045512 | N14: =N25 -> 10.862616
A15: Price | B15: ='Data Sheet'!B90 -> 386.6 | C15: ='Data Sheet'!C90 -> 465.85 | D15: ='Data Sheet'!D90 -> 326.85 | E15: ='Data Sheet'!E90 -> 174.25 | F15: ='Data Sheet'!F90 -> 71.05 | G15: ='Data Sheet'!G90 -> 301.8 | H15: ='Data Sheet'!H90 -> 433.75 | I15: ='Data Sheet'!I90 -> 420.8 | ... K15: ='Data Sheet'!K90 -> 674.45 | L15: ='Data Sheet'!B8 -> 672.3 | M15: =M13*M14 -> 1510.2847 | N15: =N13*N14 -> 355.63447
A17: RATIOS:
A18: Dividend Payout | B18: =IF('Data Sheet'!B30>0, 'Data Sheet'!B31/'Data Sheet'!B30, 0) -> 0.0058656345 | C18: =IF('Data Sheet'!C30>0, 'Data Sheet'!C31/'Data Sheet'!C30, 0) -> 0 | D18: =IF('Data Sheet'!D30>0, 'Data Sheet'!D31/'Data Sheet'!D30, 0) -> 0 | E18: =IF('Data Sheet'!E30>0, 'Data Sheet'!E31/'Data Sheet'!E30, 0) -> 0 | F18: =IF('Data Sheet'!F30>0, 'Data Sheet'!F31/'Data Sheet'!F30, 0) -> 0 | G18: =IF('Data Sheet'!G30>0, 'Data Sheet'!G31/'Data Sheet'!G30, 0) -> 0 | H18: =IF('Data Sheet'!H30>0, 'Data Sheet'!H31/'Data Sheet'!H30, 0) -> 0 | I18: =IF('Data Sheet'!I30>0, 'Data Sheet'!I31/'Data Sheet'!I30, 0) -> 0.31728583 | ... K18: =IF('Data Sheet'!K30>0, 'Data Sheet'!K31/'Data Sheet'!K30, 0) -> 0.079338843
A19: OPM | B19: =IF(B6>0,B6/B4,0) -> 0.14061845 | C19: =IF(C6>0,C6/C4,0) -> 0.10971269 | D19: =IF(D6>0,D6/D4,0) -> 0.10789788 | E19: =IF(E6>0,E6/E4,0) -> 0.081686629 | F19: =IF(F6>0,F6/F4,0) -> 0.068898034 | G19: =IF(G6>0,G6/G4,0) -> 0.12925584 | H19: =IF(H6>0,H6/H4,0) -> 0.088776328 | I19: =IF(I6>0,I6/I4,0) -> 0.091961958 | ... L19: =IF(L6>0,L6/L4,0) -> 0.12949238
G22: TRENDS: | H22: 10 YEARS | I22: 7 YEARS | J22: 5 YEARS | K22: 3 YEARS | L22: RECENT | M22: BEST | N22: WORST
G23: Sales Growth | H23: =IF(B4=0,"",POWER($K4/B4,1/9)-1) -> 0.05436433 | I23: =IF(D4=0,"",POWER($K4/D4,1/7)-1) -> 0.060452229 | J23: =IF(F4=0,"",POWER($K4/F4,1/5)-1) -> 0.1098891 | K23: =IF(H4=0,"",POWER($K4/H4, 1/3)-1) -> 0.16448229 | L23: =IF(ISERROR(MAX(IF(J4=0,"",(K4-J4)/J4),IF(K4=0,"",(L4-K4)/K4))),"",MAX(IF(J4=0,"",(K4-J4)/J4),IF(K4=0,"",(L4-K4)/K4))) -> 0.013084771 | M23: =MAX(K23:L23) -> 0.16448229 | N23: =MIN(H23:L23) -> 0.013084771
G24: OPM | H24: =IF(SUM(B4:$K$4)=0,"",SUMPRODUCT(B19:$K$19,B4:$K$4)/SUM(B4:$K$4)) -> 0.10935839 | I24: =IF(SUM(E4:$K$4)=0,"",SUMPRODUCT(E19:$K$19,E4:$K$4)/SUM(E4:$K$4)) -> 0.10580781 | J24: =IF(SUM(G4:$K$4)=0,"",SUMPRODUCT(G19:$K$19,G4:$K$4)/SUM(G4:$K$4)) -> 0.11548732 | K24: =IF(SUM(I4:$K$4)=0, "", SUMPRODUCT(I19:$K$19,I4:$K$4)/SUM(I4:$K$4)) -> 0.11876561 | L24: =L19 -> 0.12949238 | M24: =MAX(K24:L24) -> 0.12949238 | N24: =MIN(H24:L24) -> 0.10580781
G25: Price to Earning | H25: =IF(ISERROR(AVERAGEIF(B14:$L14,">0")),"",AVERAGEIF(B14:$L14,">0")) -> 18.052002 | I25: =IF(ISERROR(AVERAGEIF(E14:$L14,">0")),"",AVERAGEIF(E14:$L14,">0")) -> 22.045512 | J25: =IF(ISERROR(AVERAGEIF(G14:$L14,">0")),"",AVERAGEIF(G14:$L14,">0")) -> 22.045512 | K25: =IF(ISERROR(AVERAGEIF(I14:$L14,">0")),"",AVERAGEIF(I14:$L14,">0")) -> 22.045512 | L25: =L14 -> 10.862616 | M25: =MAX(K25:L25) -> 22.045512 | N25: =MIN(H25:L25) -> 10.862616

Sheet Quarters
A1: ='Profit & Loss'!A1 -> TATA MOTORS LTD | E1: =UPDATE | J1: SCREENER.IN
A3: Narration | B3: ='Data Sheet'!B41 -> 44926 | C3: ='Data Sheet'!C41 -> 45016 | D3: ='Data Sheet'!D41 -> 45107 | E3: ='Data Sheet'!E41 -> 45199 | F3: ='Data Sheet'!F41 -> 45291 | G3: ='Data Sheet'!G41 -> 45382 | H3: ='Data Sheet'!H41 -> 45473 | I3: ='Data Sheet'!I41 -> 45565 | ... K3: ='Data Sheet'!K41 -> 45747
A4: Sales | B4: ='Data Sheet'!B42 -> 88488.59 | C4: ='Data Sheet'!C42 -> 105932.35 | D4: ='Data Sheet'!D42 -> 102236 | E4: ='Data Sheet'!E42 -> 105129 | F4: ='Data Sheet'!F42 -> 110577 | G4: ='Data Sheet'!G42 -> 119033 | H4: ='Data Sheet'!H42 -> 108048 | I4: ='Data Sheet'!I42 -> 101450 | ... K4: ='Data Sheet'!K42 -> 119503
A5: Expenses | B5: ='Data Sheet'!B43 -> 77668.35 | C5: ='Data Sheet'!C43 -> 92817.95 | D5: ='Data Sheet'!D43 -> 89019 | E5: ='Data Sheet'!E43 -> 91362 | F5: ='Data Sheet'!F43 -> 95159 | G5: ='Data Sheet'!G43 -> 102348 | H5: ='Data Sheet'!H43 -> 92263 | I5: ='Data Sheet'!I43 -> 89291 | ... K5: ='Data Sheet'!K43 -> 102685
A6: Operating Profit | B6: ='Data Sheet'!B50 -> 10820.24 | C6: ='Data Sheet'!C50 -> 13114.4 | D6: ='Data Sheet'!D50 -> 13217 | E6: ='Data Sheet'!E50 -> 13767 | F6: ='Data Sheet'!F50 -> 15418 | G6: ='Data Sheet'!G50 -> 16685 | H6: ='Data Sheet'!H50 -> 15785 | I6: ='Data Sheet'!I50 -> 12159 | ... K6: ='Data Sheet'!K50 -> 16818
A7: Other Income | B7: ='Data Sheet'!B44 -> 1129.98 | C7: ='Data Sheet'!C44 -> 1452.86 | D7: ='Data Sheet'!D44 -> 895 | E7: ='Data Sheet'!E44 -> 1557 | F7: ='Data Sheet'!F44 -> 1604 | G7: ='Data Sheet'!G44 -> 1412 | H7: ='Data Sheet'!H44 -> 1747 | I7: ='Data Sheet'!I44 -> 1647 | ... K7: ='Data Sheet'!K44 -> 1057
A8: Depreciation | B8: ='Data Sheet'!B45 -> 6071.78 | C8: ='Data Sheet'!C45 -> 7050.2 | D8: ='Data Sheet'!D45 -> 6633 | E8: ='Data Sheet'!E45 -> 6637 | F8: ='Data Sheet'!F45 -> 6850 | G8: ='Data Sheet'!G45 -> 7143 | H8: ='Data Sheet'!H45 -> 6574 | I8: ='Data Sheet'!I45 -> 6005 | ... K8: ='Data Sheet'!K45 -> 5295
A9: Interest | B9: ='Data Sheet'!B46 -> 2675.83 | C9: ='Data Sheet'!C46 -> 2641.67 | D9: ='Data Sheet'!D46 -> 2615 | E9: ='Data Sheet'!E46 -> 2652 | F9: ='Data Sheet'!F46 -> 2485 | G9: ='Data Sheet'!G46 -> 1645 | H9: ='Data Sheet'!H46 -> 2088 | I9: ='Data Sheet'!I46 -> 2034 | ... K9: ='Data Sheet'!K46 -> 1076
A10: Profit before tax | B10: ='Data Sheet'!B47 -> 3202.61 | C10: ='Data Sheet'!C47 -> 4875.39 | D10: ='Data Sheet'!D47 -> 4864 | E10: ='Data Sheet'!E47 -> 6035 | F10: ='Data Sheet'!F47 -> 7687 | G10: ='Data Sheet'!G47 -> 9309 | H10: ='Data Sheet'!H47 -> 8870 | I10: ='Data Sheet'!I47 -> 5767 | ... K10: ='Data Sheet'!K47 -> 11504
A11: Tax | B11: ='Data Sheet'!B48 -> 262.83 | C11: ='Data Sheet'!C48 -> -620.65 | D11: ='Data Sheet'!D48 -> 1563 | E11: ='Data Sheet'!E48 -> 2203 | F11: ='Data Sheet'!F48 -> 542 | G11: ='Data Sheet'!G48 -> -8219 | H11: ='Data Sheet'!H48 -> 3178 | I11: ='Data Sheet'!I48 -> 2317 | ... K11: ='Data Sheet'!K48 -> 2948
A12: Net profit | B12: ='Data Sheet'!B49 -> 2957.71 | C12: ='Data Sheet'!C49 -> 5407.79 | D12: ='Data Sheet'!D49 -> 3203 | E12: ='Data Sheet'!E49 -> 3764 | F12: ='Data Sheet'!F49 -> 7025 | G12: ='Data Sheet'!G49 -> 17407 | H12: ='Data Sheet'!H49 -> 5566 | I12: ='Data Sheet'!I49 -> 3343 | ... K12: ='Data Sheet'!K49 -> 8470
A14: OPM | B14: =IF(B4>0,B6/B4,"") -> 0.12227836 | C14: =IF(C4>0,C6/C4,"") -> 0.12379976 | D14: =IF(D4>0,D6/D4,"") -> 0.12927931 | E14: =IF(E4>0,E6/E4,"") -> 0.1309534 | F14: =IF(F4>0,F6/F4,"") -> 0.13943225 | G14: =IF(G4>0,G6/G4,"") -> 0.14017121 | H14: =IF(H4>0,H6/H4,"") -> 0.14609248 | I14: =IF(I4>0,I6/I4,"") -> 0.11985214 | ... K14: =IF(K4>0,K6/K4,"") -> 0.14073287

Sheet Balance Sheet
A1: ='Profit & Loss'!A1 -> TATA MOTORS LTD | E1: =UPDATE | J1: SCREENER.IN
A3: Narration | B3: ='Data Sheet'!B56 -> 42460 | C3: ='Data Sheet'!C56 -> 42825 | D3: ='Data Sheet'!D56 -> 43190 | E3: ='Data Sheet'!E56 -> 43555 | F3: ='Data Sheet'!F56 -> 43921 | G3: ='Data Sheet'!G56 -> 44286 | H3: ='Data Sheet'!H56 -> 44651 | I3: ='Data Sheet'!I56 -> 45016 | ... K3: ='Data Sheet'!K56 -> 45747
A4: Equity Share Capital | B4: ='Data Sheet'!B57 -> 679.18 | C4: ='Data Sheet'!C57 -> 679.22 | D4: ='Data Sheet'!D57 -> 679.22 | E4: ='Data Sheet'!E57 -> 679.22 | F4: ='Data Sheet'!F57 -> 719.54 | G4: ='Data Sheet'!G57 -> 765.81 | H4: ='Data Sheet'!H57 -> 765.88 | I4: ='Data Sheet'!I57 -> 766.02 | ... K4: ='Data Sheet'!K57 -> 736
A5: Reserves | B5: ='Data Sheet'!B58 -> 78273.23 | C5: ='Data Sheet'!C58 -> 57382.67 | D5: ='Data Sheet'!D58 -> 94748.69 | E5: ='Data Sheet'!E58 -> 59500.34 | F5: ='Data Sheet'!F58 -> 62358.99 | G5: ='Data Sheet'!G58 -> 54480.91 | H5: ='Data Sheet'!H58 -> 43795.36 | I5: ='Data Sheet'!I58 -> 44555.77 | ... K5: ='Data Sheet'!K58 -> 115408
A6: Borrowings | B6: ='Data Sheet'!B59 -> 69359.96 | C6: ='Data Sheet'!C59 -> 78603.98 | D6: ='Data Sheet'!D59 -> 88950.47 | E6: ='Data Sheet'!E59 -> 106175.34 | F6: ='Data Sheet'!F59 -> 124787.64 | G6: ='Data Sheet'!G59 -> 142130.57 | H6: ='Data Sheet'!H59 -> 146449.03 | I6: ='Data Sheet'!I59 -> 134113.44 | ... K6: ='Data Sheet'!K59 -> 71540
A7: Other Liabilities | B7: ='Data Sheet'!B60 -> 114871.75 | C7: ='Data Sheet'!C60 -> 135914.49 | D7: ='Data Sheet'!D60 -> 142813.43 | E7: ='Data Sheet'!E60 -> 139348.59 | F7: ='Data Sheet'!F60 -> 132313.22 | G7: ='Data Sheet'!G60 -> 144192.62 | H7: ='Data Sheet'!H60 -> 138051.22 | I7: ='Data Sheet'!I60 -> 155239.2 | ... K7: ='Data Sheet'!K60 -> 189289
A8: Total | B8: ='Data Sheet'!B61 -> 263184.12 | C8: ='Data Sheet'!C61 -> 272580.36 | D8: ='Data Sheet'!D61 -> 327191.81 | E8: ='Data Sheet'!E61 -> 305703.49 | F8: ='Data Sheet'!F61 -> 320179.39 | G8: ='Data Sheet'!G61 -> 341569.91 | H8: ='Data Sheet'!H61 -> 329061.49 | I8: ='Data Sheet'!I61 -> 334674.43 | ... K8: ='Data Sheet'!K61 -> 376973
A10: Net Block | B10: ='Data Sheet'!B62 -> 107231.76 | C10: ='Data Sheet'!C62 -> 95944.08 | D10: ='Data Sheet'!D62 -> 121413.86 | E10: ='Data Sheet'!E62 -> 111234.47 | F10: ='Data Sheet'!F62 -> 127107.14 | G10: ='Data Sheet'!G62 -> 138707.61 | H10: ='Data Sheet'!H62 -> 138855.45 | I10: ='Data Sheet'!I62 -> 132079.76 | ... K10: ='Data Sheet'!K62 -> 115697
A11: Capital Work in Progress | B11: ='Data Sheet'!B63 -> 25918.94 | C11: ='Data Sheet'!C63 -> 33698.84 | D11: ='Data Sheet'!D63 -> 40033.5 | E11: ='Data Sheet'!E63 -> 31883.84 | F11: ='Data Sheet'!F63 -> 35622.29 | G11: ='Data Sheet'!G63 -> 20963.93 | H11: ='Data Sheet'!H63 -> 10251.09 | I11: ='Data Sheet'!I63 -> 14274.5 | ... K11: ='Data Sheet'!K63 -> 65806
A12: Investments | B12: ='Data Sheet'!B64 -> 23767.02 | C12: ='Data Sheet'!C64 -> 20337.92 | D12: ='Data Sheet'!D64 -> 20812.75 | E12: ='Data Sheet'!E64 -> 15770.72 | F12: ='Data Sheet'!F64 -> 16308.48 | G12: ='Data Sheet'!G64 -> 24620.28 | H12: ='Data Sheet'!H64 -> 29379.53 | I12: ='Data Sheet'!I64 -> 26379.16 | ... K12: ='Data Sheet'!K64 -> 35656
A13: Other Assets | B13: ='Data Sheet'!B65 -> 106266.4 | C13: ='Data Sheet'!C65 -> 122599.52 | D13: ='Data Sheet'!D65 -> 144931.7 | E13: ='Data Sheet'!E65 -> 146814.46 | F13: ='Data Sheet'!F65 -> 141141.48 | G13: ='Data Sheet'!G65 -> 157278.09 | H13: ='Data Sheet'!H65 -> 150575.42 | I13: ='Data Sheet'!I65 -> 161941.01 | ... K13: ='Data Sheet'!K65 -> 159814
A14: Total | B14: ='Data Sheet'!B66 -> 263184.12 | C14: ='Data Sheet'!C66 -> 272580.36 | D14: ='Data Sheet'!D66 -> 327191.81 | E14: ='Data Sheet'!E66 -> 305703.49 | F14: ='Data Sheet'!F66 -> 320179.39 | G14: ='Data Sheet'!G66 -> 341569.91 | H14: ='Data Sheet'!H66 -> 329061.49 | I14: ='Data Sheet'!I66 -> 334674.43 | ... K14: ='Data Sheet'!K66 -> 376973
A16: Working Capital | B16: =B13-B7 -> -8605.35 | C16: =C13-C7 -> -13314.97 | D16: =D13-D7 -> 2118.27 | E16: =E13-E7 -> 7465.87 | F16: =F13-F7 -> 8828.26 | G16: =G13-G7 -> 13085.47 | H16: =H13-H7 -> 12524.2 | I16: =I13-I7 -> 6701.81 | ... K16: =K13-K7 -> -29475
A17: Debtors | B17: ='Data Sheet'!B67 -> 13570.91 | C17: ='Data Sheet'!C67 -> 14075.55 | D17: ='Data Sheet'!D67 -> 19893.3 | E17: ='Data Sheet'!E67 -> 18996.17 | F17: ='Data Sheet'!F67 -> 11172.69 | G17: ='Data Sheet'!G67 -> 12679.08 | H17: ='Data Sheet'!H67 -> 12442.12 | I17: ='Data Sheet'!I67 -> 15737.97 | ... K17: ='Data Sheet'!K67 -> 13248
A18: Inventory | B18: ='Data Sheet'!B68 -> 32655.73 | C18: ='Data Sheet'!C68 -> 35085.31 | D18: ='Data Sheet'!D68 -> 42137.63 | E18: ='Data Sheet'!E68 -> 39013.73 | F18: ='Data Sheet'!F68 -> 37456.88 | G18: ='Data Sheet'!G68 -> 36088.59 | H18: ='Data Sheet'!H68 -> 35240.34 | I18: ='Data Sheet'!I68 -> 40755.39 | ... K18: ='Data Sheet'!K68 -> 47269
A20: Debtor Days | B20: =IF('Profit & Loss'!B4>0,'Balance Sheet'!B17/('Profit & Loss'!B4/365),0) -> 18.141227 | C20: =IF('Profit & Loss'!C4>0,'Balance Sheet'!C17/('Profit & Loss'!C4/365),0) -> 19.049753 | D20: =IF('Profit & Loss'!D4>0,'Balance Sheet'!D17/('Profit & Loss'!D4/365),0) -> 24.904965 | E20: =IF('Profit & Loss'!E4>0,'Balance Sheet'!E17/('Profit & Loss'!E4/365),0) -> 22.963631 | F20: =IF('Profit & Loss'!F4>0,'Balance Sheet'!F17/('Profit & Loss'!F4/365),0) -> 15.620575 | G20: =IF('Profit & Loss'!G4>0,'Balance Sheet'!G17/('Profit & Loss'!G4/365),0) -> 18.526667 | H20: =IF('Profit & Loss'!H4>0,'Balance Sheet'!H17/('Profit & Loss'!H4/365),0) -> 16.309265 | I20: =IF('Profit & Loss'!I4>0,'Balance Sheet'!I17/('Profit & Loss'!I4/365),0) -> 16.603779 | ... K20: =IF('Profit & Loss'!K4>0,'Balance Sheet'!K17/('Profit & Loss'!K4/365),0) -> 10.997441
A21: Inventory Turnover | B21: =IF('Balance Sheet'!B18>0,'Profit & Loss'!B4/'Balance Sheet'!B18,0) -> 8.3613381 | C21: =IF('Balance Sheet'!C18>0,'Profit & Loss'!C4/'Balance Sheet'!C18,0) -> 7.6867643 | D21: =IF('Balance Sheet'!D18>0,'Profit & Loss'!D4/'Balance Sheet'!D18,0) -> 6.9190052 | E21: =IF('Balance Sheet'!E18>0,'Profit & Loss'!E4/'Balance Sheet'!E18,0) -> 7.7392856 | F21: =IF('Balance Sheet'!F18>0,'Profit & Loss'!F4/'Balance Sheet'!F18,0) -> 6.9698269 | G21: =IF('Balance Sheet'!G18>0,'Profit & Loss'!G4/'Balance Sheet'!G18,0) -> 6.9217099 | H21: =IF('Balance Sheet'!H18>0,'Profit & Loss'!H4/'Balance Sheet'!H18,0) -> 7.9015588 | I21: =IF('Balance Sheet'!I18>0,'Profit & Loss'!I4/'Balance Sheet'!I18,0) -> 8.4888642 | ... K21: =IF('Balance Sheet'!K18>0,'Profit & Loss'!K4/'Balance Sheet'!K18,0) -> 9.3019738
A23: Return on Equity | B23: =IF(SUM('Balance Sheet'!B4:B5)>0,'Profit & Loss'!B12/SUM('Balance Sheet'!B4:B5),"") -> 0.14666189 | C23: =IF(SUM('Balance Sheet'!C4:C5)>0,'Profit & Loss'!C12/SUM('Balance Sheet'!C4:C5),"") -> 0.12838645 | D23: =IF(SUM('Balance Sheet'!D4:D5)>0,'Profit & Loss'!D12/SUM('Balance Sheet'!D4:D5),"") -> 0.094195818 | E23: =IF(SUM('Balance Sheet'!E4:E5)>0,'Profit & Loss'!E12/SUM('Balance Sheet'!E4:E5),"") -> -0.47900367 | F23: =IF(SUM('Balance Sheet'!F4:F5)>0,'Profit & Loss'!F12/SUM('Balance Sheet'!F4:F5),"") -> -0.19136226 | G23: =IF(SUM('Balance Sheet'!G4:G5)>0,'Profit & Loss'!G12/SUM('Balance Sheet'!G4:G5),"") -> -0.24347853 | H23: =IF(SUM('Balance Sheet'!H4:H5)>0,'Profit & Loss'!H12/SUM('Balance Sheet'!H4:H5),"") -> -0.25675834 | I23: =IF(SUM('Balance Sheet'!I4:I5)>0,'Profit & Loss'!I12/SUM('Balance Sheet'!I4:I5),"") -> 0.053269961 | ... K23: =IF(SUM('Balance Sheet'!K4:K5)>0,'Profit & Loss'!K12/SUM('Balance Sheet'!K4:K5),"") -> 0.23961634
A24: Return on Capital Emp | C24: =IF((B4+B5+B6+C4+C5+C6)>0,('Profit & Loss'!C10+'Profit & Loss'!C9)*2/(B4+B5+B6+C4+C5+C6),"") -> 0.095114631 | D24: =IF((C4+C5+C6+D4+D5+D6)>0,('Profit & Loss'!D10+'Profit & Loss'!D9)*2/(C4+C5+C6+D4+D5+D6),"") -> 0.098658176 | E24: =IF((D4+D5+D6+E4+E5+E6)>0,('Profit & Loss'!E10+'Profit & Loss'!E9)*2/(D4+D5+D6+E4+E5+E6),"") -> -0.14605144 | F24: =IF((E4+E5+E6+F4+F5+F6)>0,('Profit & Loss'!F10+'Profit & Loss'!F9)*2/(E4+E5+E6+F4+F5+F6),"") -> -0.018839365 | G24: =IF((F4+F5+F6+G4+G5+G6)>0,('Profit & Loss'!G10+'Profit & Loss'!G9)*2/(F4+F5+F6+G4+G5+G6),"") -> -0.012340819 | H24: =IF((G4+G5+G6+H4+H5+H6)>0,('Profit & Loss'!H10+'Profit & Loss'!H9)*2/(G4+G5+G6+H4+H5+H6),"") -> 0.011887353 | I24: =IF((H4+H5+H6+I4+I5+I6)>0,('Profit & Loss'!I10+'Profit & Loss'!I9)*2/(H4+H5+H6+I4+I5+I6),"") -> 0.073529898 | J24: =IF((I4+I5+I6+J4+J5+J6)>0,('Profit & Loss'!J10+'Profit & Loss'!J9)*2/(I4+I5+I6+J4+J5+J6),"") -> 0.19039483 | K24: =IF((J4+J5+J6+K4+K5+K6)>0,('Profit & Loss'!K10+'Profit & Loss'!K9)*2/(J4+J5+J6+K4+K5+K6),"") -> 0.23026014

Sheet Cash Flow
A1: ='Balance Sheet'!A1 -> TATA MOTORS LTD | E1: =UPDATE | J1: SCREENER.IN
A3: Narration | B3: ='Data Sheet'!B81 -> 42460 | C3: ='Data Sheet'!C81 -> 42825 | D3: ='Data Sheet'!D81 -> 43190 | E3: ='Data Sheet'!E81 -> 43555 | F3: ='Data Sheet'!F81 -> 43921 | G3: ='Data Sheet'!G81 -> 44286 | H3: ='Data Sheet'!H81 -> 44651 | I3: ='Data Sheet'!I81 -> 45016 | ... K3: ='Data Sheet'!K81 -> 45747
A4: Cash from Operating Activity | B4: ='Data Sheet'!B82 -> 37899.54 | C4: ='Data Sheet'!C82 -> 30199.25 | D4: ='Data Sheet'!D82 -> 23857.42 | E4: ='Data Sheet'!E82 -> 18890.75 | F4: ='Data Sheet'!F82 -> 26632.94 | G4: ='Data Sheet'!G82 -> 29000.51 | H4: ='Data Sheet'!H82 -> 14282.83 | I4: ='Data Sheet'!I82 -> 35388.01 | ... K4: ='Data Sheet'!K82 -> 63102
A5: Cash from Investing Activity | B5: ='Data Sheet'!B83 -> -36693.9 | C5: ='Data Sheet'!C83 -> -39571.4 | D5: ='Data Sheet'!D83 -> -25139.14 | E5: ='Data Sheet'!E83 -> -20878.07 | F5: ='Data Sheet'!F83 -> -33114.55 | G5: ='Data Sheet'!G83 -> -25672.5 | H5: ='Data Sheet'!H83 -> -4443.66 | I5: ='Data Sheet'!I83 -> -15417.17 | ... K5: ='Data Sheet'!K83 -> -49982
A6: Cash from Financing Activity | B6: ='Data Sheet'!B84 -> -3795.12 | C6: ='Data Sheet'!C84 -> 6205.3 | D6: ='Data Sheet'!D84 -> 2011.71 | E6: ='Data Sheet'!E84 -> 8830.37 | F6: ='Data Sheet'!F84 -> 3389.61 | G6: ='Data Sheet'!G84 -> 9904.2 | H6: ='Data Sheet'!H84 -> -3380.17 | I6: ='Data Sheet'!I84 -> -26242.9 | ... K6: ='Data Sheet'!K84 -> -18786
A7: Net Cash Flow | B7: ='Data Sheet'!B85 -> -2589.48 | C7: ='Data Sheet'!C85 -> -3166.85 | D7: ='Data Sheet'!D85 -> 729.99 | E7: ='Data Sheet'!E85 -> 6843.05 | F7: ='Data Sheet'!F85 -> -3092 | G7: ='Data Sheet'!G85 -> 13232.21 | H7: ='Data Sheet'!H85 -> 6459 | I7: ='Data Sheet'!I85 -> -6272.06 | ... K7: ='Data Sheet'!K85 -> -5666

Sheet Data Sheet
A1: COMPANY NAME | B1: TATA MOTORS LTD | E1: =IF(B2<>B3, "A NEW VERSION OF THE WORKSHEET IS AVAILABLE", "")
A2: LATEST VERSION | B2: 2.1 | E2: PLEASE DO NOT MAKE ANY CHANGES TO THIS SHEET
A3: CURRENT VERSION | B3: 2.1
A5: META
A6: Number of shares | B6: =IF(B9>0, B9/B8, 0) -> 368.14623
A7: Face Value | B7: 2
A8: Current Price | B8: 672.3
A9: Market Capitalization | B9: 247504.71
A15: PROFIT & LOSS
A16: Report Date | B16: 42460 | C16: 42825 | D16: 43190 | E16: 43555 | F16: 43921 | G16: 44286 | H16: 44651 | I16: 45016 | J16: 45382 | K16: 45747
A17: Sales | B17: 273045.6 | C17: 269692.51 | D17: 291550.48 | E17: 301938.4 | F17: 261067.97 | G17: 249794.75 | H17: 278453.62 | I17: 345966.97 | J17: 434016 | K17: 439695
A18: Raw Material Cost | B18: 166134.01 | C18: 173294.08 | D18: 187896.58 | E18: 194267.91 | F18: 164899.82 | G18: 153607.36 | H18: 179295.33 | I18: 231251.26 | J18: 274321 | K18: 268950
A19: Change in Inventory | B19: 2750.99 | C19: 7399.92 | D19: 2046.58 | E19: -2053.28 | F19: -2231.19 | G19: -4684.16 | H19: -1590.49 | I19: 4781.62 | J19: 1566 | K19: -2836
A20: Power and Fuel | B20: 1143.63 | C20: 1159.82 | D20: 1308.08 | E20: 1585.93 | F20: 1264.95 | G20: 1112.87 | H20: 2178.29 | I20: 2513.33 | J20: 2189 | K20: 2443
A21: Other Mfr. Exp | B21: 12101.53 | C21: 10067.37 | D21: 10971.66 | E21: 11694.54 | F21: 11541.51 | G21: 8273.17 | H21: 9427.38 | I21: 11765.97 | J21: 17446 | K21: 18813
A22: Employee Cost | B22: 28880.89 | C22: 28332.89 | D22: 30300.09 | E22: 33243.87 | F22: 30438.6 | G22: 27648.48 | H22: 30808.52 | I22: 33654.7 | J22: 41990 | K22: 47767
A23: Selling and admin | B23: 21991.9 | C23: 30039.38 | D23: 31004.58 | E23: 32719.8 | F23: 29248.32 | G23: 23015.79 | H23: 29205.4 | I23: 34839.19 | J23: 42765 | K23: 47099
A24: Other Expenses | B24: 7149.38 | C24: 4610.2 | D24: 658.39 | E24: 1708.74 | F24: 3456.51 | G24: -834.51 | H24: 1228.12 | I24: 4908.34 | J24: -953 | K24: -3429
A25: Other Income | B25: -2669.62 | C25: 1869.1 | D25: 5932.73 | E25: -26686.25 | F25: 101.71 | G25: -11117.83 | H25: 2424.05 | I25: 6663.97 | J25: 4792 | K25: 11774
A26: Depreciation | B26: 16710.78 | C26: 17904.99 | D26: 21553.59 | E26: 23590.63 | F26: 21425.43 | G26: 23546.71 | H26: 24835.69 | I26: 24860.36 | J26: 27239 | K26: 23256
A27: Interest | B27: 4889.08 | C27: 4238.01 | D27: 4681.79 | E27: 5758.6 | F27: 7243.33 | G27: 8097.17 | H27: 9311.86 | I27: 10225.48 | J27: 7594 | K27: 5083
... A30: Net profit | B30: 11579.31 | C30: 7454.36 | D30: 8988.91 | E30: -28826.23 | F30: -12070.85 | G30: -13451.39 | H30: -11441.47 | I30: 2414.29 | J30: 31399 | K30: 27830
A31: Dividend Amount | B31: 67.92 | I31: 766.02 | J31: 2301 | K31: 2208
A32: EBITDA | B32: =B30+B27+B29+B26 -> 36204.22 | C32: =C30+C27+C29+C26 -> 32848.59 | D32: =D30+D27+D29+D26 -> 39566.22 | E32: =E30+E27+E29+E26 -> -1914.45 | F32: =F30+F27+F29+F26 -> 16993.16 | G32: =G30+G27+G29+G26 -> 20734.35 | H32: =H30+H27+H29+H26 -> 26937.37 | I32: =I30+I27+I29+I26 -> 38204.19 | ... K32: =K30+K27+K29+K26 -> 66671
A40: Quarters
A41: Report Date | B41: 44926 | C41: 45016 | D41: 45107 | E41: 45199 | F41: 45291 | G41: 45382 | H41: 45473 | I41: 45565 | J41: 45657 | K41: 45747
A42: Sales | B42: 88488.59 | C42: 105932.35 | D42: 102236 | E42: 105129 | F42: 110577 | G42: 119033 | H42: 108048 | I42: 101450 | J42: 112608 | K42: 119503
A43: Expenses | B43: 77668.35 | C43: 92817.95 | D43: 89019 | E43: 91362 | F43: 95159 | G43: 102348 | H43: 92263 | I43: 89291 | J43: 100185 | K43: 102685
A44: Other Income | B44: 1129.98 | C44: 1452.86 | D44: 895 | E44: 1557 | F44: 1604 | G44: 1412 | H44: 1747 | I44: 1647 | J44: 1700 | K44: 1057
A45: Depreciation | B45: 6071.78 | C45: 7050.2 | D45: 6633 | E45: 6637 | F45: 6850 | G45: 7143 | H45: 6574 | I45: 6005 | J45: 5399 | K45: 5295
A46: Interest | B46: 2675.83 | C46: 2641.67 | D46: 2615 | E46: 2652 | F46: 2485 | G46: 1645 | H46: 2088 | I46: 2034 | J46: 1119 | K46: 1076
A47: Profit before tax | B47: 3202.61 | C47: 4875.39 | D47: 4864 | E47: 6035 | F47: 7687 | G47: 9309 | H47: 8870 | I47: 5767 | J47: 7605 | K47: 11504
A48: Tax | B48: 262.83 | C48: -620.65 | D48: 1563 | E48: 2203 | F48: 542 | G48: -8219 | H48: 3178 | I48: 2317 | J48: 2120 | K48: 2948
A49: Net profit | B49: 2957.71 | C49: 5407.79 | D49: 3203 | E49: 3764 | F49: 7025 | G49: 17407 | H49: 5566 | I49: 3343 | J49: 5406 | K49: 8470
A50: Operating Profit | B50: 10820.24 | C50: 13114.4 | D50: 13217 | E50: 13767 | F50: 15418 | G50: 16685 | H50: 15785 | I50: 12159 | J50: 12423 | K50: 16818
A55: BALANCE SHEET
A56: Report Date | B56: 42460 | C56: 42825 | D56: 43190 | E56: 43555 | F56: 43921 | G56: 44286 | H56: 44651 | I56: 45016 | J56: 45382 | K56: 45747
A57: Equity Share Capital | B57: 679.18 | C57: 679.22 | D57: 679.22 | E57: 679.22 | F57: 719.54 | G57: 765.81 | H57: 765.88 | I57: 766.02 | J57: 767 | K57: 736
A58: Reserves | B58: 78273.23 | C58: 57382.67 | D58: 94748.69 | E58: 59500.34 | F58: 62358.99 | G58: 54480.91 | H58: 43795.36 | I58: 44555.77 | J58: 84151 | K58: 115408
A59: Borrowings | B59: 69359.96 | C59: 78603.98 | D59: 88950.47 | E59: 106175.34 | F59: 124787.64 | G59: 142130.57 | H59: 146449.03 | I59: 134113.44 | J59: 107264 | K59: 71540
A60: Other Liabilities | B60: 114871.75 | C60: 135914.49 | D60: 142813.43 | E60: 139348.59 | F60: 132313.22 | G60: 144192.62 | H60: 138051.22 | I60: 155239.2 | J60: 177339 | K60: 189289
A61: Total | B61: 263184.12 | C61: 272580.36 | D61: 327191.81 | E61: 305703.49 | F61: 320179.39 | G61: 341569.91 | H61: 329061.49 | I61: 334674.43 | J61: 369521 | K61: 376973
A62: Net Block | B62: 107231.76 | C62: 95944.08 | D62: 121413.86 | E62: 111234.47 | F62: 127107.14 | G62: 138707.61 | H62: 138855.45 | I62: 132079.76 | J62: 121285 | K62: 115697
A63: Capital Work in Progress | B63: 25918.94 | C63: 33698.84 | D63: 40033.5 | E63: 31883.84 | F63: 35622.29 | G63: 20963.93 | H63: 10251.09 | I63: 14274.5 | J63: 35698 | K63: 65806
A64: Investments | B64: 23767.02 | C64: 20337.92 | D64: 20812.75 | E64: 15770.72 | F64: 16308.48 | G64: 24620.28 | H64: 29379.53 | I64: 26379.16 | J64: 22971 | K64: 35656
A65: Other Assets | B65: 106266.4 | C65: 122599.52 | D65: 144931.7 | E65: 146814.46 | F65: 141141.48 | G65: 157278.09 | H65: 150575.42 | I65: 161941.01 | J65: 189567 | K65: 159814
A66: Total | B66: 263184.12 | C66: 272580.36 | D66: 327191.81 | E66: 305703.49 | F66: 320179.39 | G66: 341569.91 | H66: 329061.49 | I66: 334674.43 | J66: 369521 | K66: 376973
A67: Receivables | B67: 13570.91 | C67: 14075.55 | D67: 19893.3 | E67: 18996.17 | F67: 11172.69 | G67: 12679.08 | H67: 12442.12 | I67: 15737.97 | J67: 16952 | K67: 13248
... A70: No. of Equity Shares | B70: 3395930306 | C70: 3396100719 | D70: 3396100719 | E70: 3396100719 | F70: 3597726185 | G70: 3829060661 | H70: 3829414903 | I70: 3830097221 | J70: 3832491897 | K70: 3681348742
A71: New Bonus Shares
A72: Face value | B72: 2 | C72: 2 | D72: 2 | E72: 2 | F72: 2 | G72: 2 | H72: 2 | I72: 2 | J72: 2 | K72: 2
A75: Total Asset | B75: =B66 -> 263184.12 | C75: =C66 -> 272580.36 | D75: =D66 -> 327191.81 | E75: =E66 -> 305703.49 | F75: =F66 -> 320179.39 | G75: =G66 -> 341569.91 | H75: =H66 -> 329061.49 | I75: =I66 -> 334674.43 | ... K75: =K66 -> 376973
A80: CASH FLOW:
A81: Report Date | B81: 42460 | C81: 42825 | D81: 43190 | E81: 43555 | F81: 43921 | G81: 44286 | H81: 44651 | I81: 45016 | J81: 45382 | K81: 45747
A82: Cash from Operating Activity | B82: 37899.54 | C82: 30199.25 | D82: 23857.42 | E82: 18890.75 | F82: 26632.94 | G82: 29000.51 | H82: 14282.83 | I82: 35388.01 | J82: 67915 | K82: 63102
A83: Cash from Investing Activity | B83: -36693.9 | C83: -39571.4 | D83: -25139.14 | E83: -20878.07 | F83: -33114.55 | G83: -25672.5 | H83: -4443.66 | I83: -15417.17 | J83: -22781 | K83: -49982
A84: Cash from Financing Activity | B84: -3795.12 | C84: 6205.3 | D84: 2011.71 | E84: 8830.37 | F84: 3389.61 | G84: 9904.2 | H84: -3380.17 | I84: -26242.9 | J84: -37006 | K84: -18786
A85: Net Cash Flow | B85: -2589.48 | C85: -3166.85 | D85: 729.99 | E85: 6843.05 | F85: -3092 | G85: 13232.21 | H85: 6459 | I85: -6272.06 | J85: 8128 | K85: -5666
A90: PRICE: | B90: 386.6 | C90: 465.85 | D90: 326.85 | E90: 174.25 | F90: 71.05 | G90: 301.8 | H90: 433.75 | I90: 420.8 | J90: 992.8 | K90: 674.45
A92: DERIVED:
A93: Adjusted Equity Shares in Cr | B93: 288.72 | C93: 288.73 | D93: 288.73 | E93: 288.73 | F93: 308.9 | G93: 332.03 | H93: 332.07 | I93: 332.13 | J93: 332.37 | K93: 368.13

Sheet HistoricaIFS
B2: ="Historial Financial Statement - "&'Data Sheet'!B1 -> Historial Financial Statement - TATA MOTORS LTD
B3: Years | C3: ='Data Sheet'!B16 -> 42460 | D3: ='Data Sheet'!C16 -> 42825 | E3: ='Data Sheet'!D16 -> 43190 | F3: ='Data Sheet'!E16 -> 43555 | G3: ='Data Sheet'!F16 -> 43921 | H3: ='Data Sheet'!G16 -> 44286 | I3: ='Data Sheet'!H16 -> 44651 | J3: ='Data Sheet'!I16 -> 45016 | ... L3: ='Data Sheet'!K16 -> 45747 | M3: LTM
A4: # | B4: Income Statement
B5: Sales | C5: =IFERROR('Data Sheet'!B17,0) -> 273045.6 | D5: =IFERROR('Data Sheet'!C17,0) -> 269692.51 | E5: =IFERROR('Data Sheet'!D17,0) -> 291550.48 | F5: =IFERROR('Data Sheet'!E17,0) -> 301938.4 | G5: =IFERROR('Data Sheet'!F17,0) -> 261067.97 | H5: =IFERROR('Data Sheet'!G17,0) -> 249794.75 | I5: =IFERROR('Data Sheet'!H17,0) -> 278453.62 | J5: =IFERROR('Data Sheet'!I17,0) -> 345966.97 | ... L5: =IFERROR('Data Sheet'!K17,0) -> 439695 | M5: =IFERROR(SUM('Data Sheet'!H42:K42),0) -> 441609
B6: Sales Growth | C6: - | D6: =D5/C5-1 -> -0.01228033 | E6: =E5/D5-1 -> 0.081047746 | F6: =F5/E5-1 -> 0.035629919 | G6: =G5/F5-1 -> -0.13536016 | H6: =H5/G5-1 -> -0.043181168 | I6: =I5/H5-1 -> 0.11472967 | J6: =J5/I5-1 -> 0.24245815 | K6: =K5/J5-1 -> 0.25450126 | ... M6: =M5/L5-1 -> 0.0043530174
B8: COGS | C8: =IFERROR(SUM('Data Sheet'!B18,'Data Sheet'!B20:B22)-1*'Data Sheet'!B19,0) -> 205509.07 | D8: =IFERROR(SUM('Data Sheet'!C18,'Data Sheet'!C20:C22)-1*'Data Sheet'!C19,0) -> 205454.24 | E8: =IFERROR(SUM('Data Sheet'!D18,'Data Sheet'!D20:D22)-1*'Data Sheet'!D19,0) -> 228429.83 | F8: =IFERROR(SUM('Data Sheet'!E18,'Data Sheet'!E20:E22)-1*'Data Sheet'!E19,0) -> 242845.53 | G8: =IFERROR(SUM('Data Sheet'!F18,'Data Sheet'!F20:F22)-1*'Data Sheet'!F19,0) -> 210376.07 | H8: =IFERROR(SUM('Data Sheet'!G18,'Data Sheet'!G20:G22)-1*'Data Sheet'!G19,0) -> 195326.04 | I8: =IFERROR(SUM('Data Sheet'!H18,'Data Sheet'!H20:H22)-1*'Data Sheet'!H19,0) -> 223300.01 | J8: =IFERROR(SUM('Data Sheet'!I18,'Data Sheet'!I20:I22)-1*'Data Sheet'!I19,0) -> 274403.64 | ... L8: =IFERROR(SUM('Data Sheet'!K18,'Data Sheet'!K20:K22)-1*'Data Sheet'!K19,0) -> 340809 | M8: =IFERROR(SUM(Quarters!H5:K5),0) -> 384424
B9: Gross Margine(COGS % Sales) | C9: =C8/C5 -> 0.75265476 | D9: =D8/D5 -> 0.76180922 | E9: =E8/E5 -> 0.7835001 | F9: =F8/F5 -> 0.80428833 | G9: =G8/G5 -> 0.80582873 | H9: =H8/H5 -> 0.78194614 | I9: =I8/I5 -> 0.80192892 | J9: =J8/J5 -> 0.79314982 | ... M9: =M8/M5 -> 0.87050762
B11: Gross Profit | C11: =C5-C8 -> 67536.53 | D11: =D5-D8 -> 64238.27 | E11: =E5-E8 -> 63120.65 | F11: =F5-F8 -> 59092.87 | G11: =G5-G8 -> 50691.9 | H11: =H5-H8 -> 54468.71 | I11: =I5-I8 -> 55153.61 | J11: =J5-J8 -> 71563.33 | ... M11: =M5-M8 -> 57185
B12: Gross Profit % Sales | C12: =C11/C5 -> 0.24734524 | D12: =D11/D5 -> 0.23819078 | E12: =E11/E5 -> 0.2164999 | F12: =F11/F5 -> 0.19571167 | G12: =G11/G5 -> 0.19417127 | H12: =H11/H5 -> 0.21805386 | I12: =I11/I5 -> 0.19807108 | J12: =J11/J5 -> 0.20685018 | ... M12: =M11/M5 -> 0.12949238
B14: Selling & Gernal Expenses | C14: =IFERROR(SUM('Data Sheet'!B23:B24),0) -> 29141.28 | D14: =IFERROR(SUM('Data Sheet'!C23:C24),0) -> 34649.58 | E14: =IFERROR(SUM('Data Sheet'!D23:D24),0) -> 31662.97 | F14: =IFERROR(SUM('Data Sheet'!E23:E24),0) -> 34428.54 | G14: =IFERROR(SUM('Data Sheet'!F23:F24),0) -> 32704.83 | H14: =IFERROR(SUM('Data Sheet'!G23:G24),0) -> 22181.28 | I14: =IFERROR(SUM('Data Sheet'!H23:H24),0) -> 30433.52 | J14: =IFERROR(SUM('Data Sheet'!I23:I24),0) -> 39747.53 | ... L14: =IFERROR(SUM('Data Sheet'!K23:K24),0) -> 43670
B15: S & G Exp % Sales | C15: =C14/C5 -> 0.10672679 | D15: =D14/D5 -> 0.1284781 | E15: =E14/E5 -> 0.10860202 | F15: =F14/F5 -> 0.11402505 | G15: =G14/G5 -> 0.12527324 | H15: =H14/H5 -> 0.088798023 | I15: =I14/I5 -> 0.10929475 | J15: =J14/J5 -> 0.11488822 | ... M15: =M14/M5 -> 0
B17: EBITDA | C17: =C11-C14 -> 38395.25 | D17: =D11-D14 -> 29588.69 | E17: =E11-E14 -> 31457.68 | F17: =F11-F14 -> 24664.33 | G17: =G11-G14 -> 17987.07 | H17: =H11-H14 -> 32287.43 | I17: =I11-I14 -> 24720.09 | J17: =J11-J14 -> 31815.8 | ... M17: =M11-M14 -> 57185
B18: EBITDA % Sales | C18: =C17/C5 -> 0.14061845 | D18: =D17/D5 -> 0.10971269 | E18: =E17/E5 -> 0.10789788 | F18: =F17/F5 -> 0.081686629 | G18: =G17/G5 -> 0.068898034 | H18: =H17/H5 -> 0.12925584 | I18: =I17/I5 -> 0.088776328 | J18: =J17/J5 -> 0.091961958 | ... M18: =M17/M5 -> 0.12949238
B20: Interest | C20: 4889.08 | D20: 4238.01 | E20: 4681.79 | F20: 5758.6 | G20: 7243.33 | H20: 8097.17 | I20: 9311.86 | J20: 10225.48 | K20: 7594 | L20: 5083 | M20: =IFERROR(SUM('Data Sheet'!H46:K46),0) -> 6317
B21: Interest % Sales | C21: =C20/C5 -> 0.017905727 | D21: =D20/D5 -> 0.01571423 | E21: =E20/E5 -> 0.016058248 | F21: =F20/F5 -> 0.019072102 | G21: =G20/G5 -> 0.027744997 | H21: =H20/H5 -> 0.032415293 | I21: =I20/I5 -> 0.033441332 | J21: =J20/J5 -> 0.029556232 | ... M21: =M20/M5 -> 0.014304509
B23: Deprisiation | C23: =IFERROR('Data Sheet'!B26,0) -> 16710.78 | D23: =IFERROR('Data Sheet'!C26,0) -> 17904.99 | E23: =IFERROR('Data Sheet'!D26,0) -> 21553.59 | F23: =IFERROR('Data Sheet'!E26,0) -> 23590.63 | G23: =IFERROR('Data Sheet'!F26,0) -> 21425.43 | H23: =IFERROR('Data Sheet'!G26,0) -> 23546.71 | I23: =IFERROR('Data Sheet'!H26,0) -> 24835.69 | J23: =IFERROR('Data Sheet'!I26,0) -> 24860.36 | ... L23: =IFERROR('Data Sheet'!K26,0) -> 23256 | M23: =IFERROR(SUM('Data Sheet'!H45:K45),0) -> 23273
B24: Deprisiation % Sales | C24: =C23/C5 -> 0.061201426 | D24: =D23/D5 -> 0.066390387 | E24: =E23/E5 -> 0.073927472 | F24: =F23/F5 -> 0.078130605 | G24: =G23/G5 -> 0.082068398 | H24: =H23/H5 -> 0.094264231 | I24: =I23/I5 -> 0.089191478 | J24: =J23/J5 -> 0.071857611 | ... M24: =M23/M5 -> 0.052700466
B26: EBT | C26: =IFERROR(C17-SUM(C20,C23),0) -> 16795.39 | D26: =IFERROR(D17-SUM(D20,D23),0) -> 7445.69 | E26: =IFERROR(E17-SUM(E20,E23),0) -> 5222.3 | F26: =IFERROR(F17-SUM(F20,F23),0) -> -4684.9 | G26: =IFERROR(G17-SUM(G20,G23),0) -> -10681.69 | H26: =IFERROR(H17-SUM(H20,H23),0) -> 643.55 | I26: =IFERROR(I17-SUM(I20,I23),0) -> -9427.46 | J26: =IFERROR(J17-SUM(J20,J23),0) -> -3270.04 | ... M26: =IFERROR(M17-SUM(M20,M23),0) -> 27595 | O26: =L26-K26-1 -> 3885
B27: EBT % Sales | C27: =C26/C5 -> 0.061511301 | D27: =D26/D5 -> 0.027608071 | E27: =E26/E5 -> 0.017912164 | F27: =F26/F5 -> -0.015516079 | G27: =G26/G5 -> -0.04091536 | H27: =H26/H5 -> 0.0025763152 | I27: =I26/I5 -> -0.033856482 | J27: =J26/J5 -> -0.009451885 | ... M27: =M26/M5 -> 0.062487404
B29: TAX | C29: =IFERROR('Data Sheet'!B48,0) -> 262.83 | D29: =IFERROR('Data Sheet'!C48,0) -> -620.65 | E29: =IFERROR('Data Sheet'!D48,0) -> 1563 | F29: =IFERROR('Data Sheet'!E48,0) -> 2203 | G29: =IFERROR('Data Sheet'!F48,0) -> 542 | H29: =IFERROR('Data Sheet'!G48,0) -> -8219 | I29: =IFERROR('Data Sheet'!H48,0) -> 3178 | J29: =IFERROR('Data Sheet'!I48,0) -> 2317 | ... L29: =IFERROR('Data Sheet'!K48,0) -> 2948 | M29: =IFERROR(SUM('Data Sheet'!H48:K48),0) -> 10563
B30: TAX % Sales | C30: =C29/C5 -> 0.00096258647 | D30: =D29/D5 -> -0.0023013246 | E30: =E29/E5 -> 0.0053609927 | F30: =F29/F5 -> 0.0072961902 | G30: =G29/G5 -> 0.0020760877 | H30: =H29/H5 -> -0.032903013 | I30: =I29/I5 -> 0.011413032 | J30: =J29/J5 -> 0.0066971711 | ... M30: =M29/M5 -> 0.023919349
B32: Net Profit | C32: ='Data Sheet'!B49 -> 2957.71 | D32: ='Data Sheet'!C49 -> 5407.79 | E32: ='Data Sheet'!D49 -> 3203 | F32: ='Data Sheet'!E49 -> 3764 | G32: ='Data Sheet'!F49 -> 7025 | H32: ='Data Sheet'!G49 -> 17407 | I32: ='Data Sheet'!H49 -> 5566 | J32: ='Data Sheet'!I49 -> 3343 | ... L32: ='Data Sheet'!K49 -> 8470 | M32: =IFERROR(SUM('Data Sheet'!H49:K49),0) -> 22785
B33: Net Profit % Sales | C33: =IFERROR(C32/C5,0) -> 0.010832293 | D33: =IFERROR(D32/D5,0) -> 0.020051688 | E33: =IFERROR(E32/E5,0) -> 0.010986091 | F33: =IFERROR(F32/F5,0) -> 0.012466119 | G33: =IFERROR(G32/G5,0) -> 0.026908701 | H33: =IFERROR(H32/H5,0) -> 0.069685212 | I33: =IFERROR(I32/I5,0) -> 0.019988966 | J33: =IFERROR(J32/J5,0) -> 0.0096627721 | ... M33: =IFERROR(M32/M5,0) -> 0.051595416
B35: No Of Equity Share | C35: =IFERROR('Data Sheet'!B93,0) -> 288.72 | D35: =IFERROR('Data Sheet'!C93,0) -> 288.73 | E35: =IFERROR('Data Sheet'!D93,0) -> 288.73 | F35: =IFERROR('Data Sheet'!E93,0) -> 288.73 | G35: =IFERROR('Data Sheet'!F93,0) -> 308.9 | H35: =IFERROR('Data Sheet'!G93,0) -> 332.03 | I35: =IFERROR('Data Sheet'!H93,0) -> 332.07 | J35: =IFERROR('Data Sheet'!I93,0) -> 332.13 | ... L35: =IFERROR('Data Sheet'!K93,0) -> 368.13
B37: EPS | C37: =IFERROR(C32/C35,0) -> 10.244216 | D37: =IFERROR(D32/D35,0) -> 18.729574 | E37: =IFERROR(E32/E35,0) -> 11.093409 | F37: =IFERROR(F32/F35,0) -> 13.036401 | G37: =IFERROR(G32/G35,0) -> 22.741988 | H37: =IFERROR(H32/H35,0) -> 52.425986 | I37: =IFERROR(I32/I35,0) -> 16.761526 | J37: =IFERROR(J32/J35,0) -> 10.065336 | ... M37: =IFERROR(M32/M35,0) -> 0
B38: EPS Growth % | D38: =IFERROR(D37/C37-1,0) -> 0.82830727 | E38: =IFERROR(E37/D37-1,0) -> -0.40770629 | F38: =IFERROR(F37/E37-1,0) -> 0.1751483 | G38: =IFERROR(G37/F37-1,0) -> 0.74449897 | H38: =IFERROR(H37/G37-1,0) -> 1.3052508 | I38: =IFERROR(I37/H37-1,0) -> -0.6802821 | J38: =IFERROR(J37/I37-1,0) -> -0.39949765 | K38: =IFERROR(K37/J37-1,0) -> 0.61594269 | ... M38: =IFERROR(M37/L37-1,0) -> -1
B40: Dividend per Share | C40: =IFERROR('Data Sheet'!B31/HistoricaIFS!C35,0) -> 0.23524522 | D40: =IFERROR('Data Sheet'!C31/HistoricaIFS!D35,0) -> 0 | E40: =IFERROR('Data Sheet'!D31/HistoricaIFS!E35,0) -> 0 | F40: =IFERROR('Data Sheet'!E31/HistoricaIFS!F35,0) -> 0 | G40: =IFERROR('Data Sheet'!F31/HistoricaIFS!G35,0) -> 0 | H40: =IFERROR('Data Sheet'!G31/HistoricaIFS!H35,0) -> 0 | I40: =IFERROR('Data Sheet'!H31/HistoricaIFS!I35,0) -> 0 | J40: =IFERROR('Data Sheet'!I31/HistoricaIFS!J35,0) -> 2.3063861 | ... M40: =IFERROR('Data Sheet'!L31/HistoricaIFS!M35,0) -> 0
B41: Dividend Payout Ratio | C41: =C40/C37 -> 0.022963712 | D41: =D40/D37 -> 0 | E41: =E40/E37 -> 0 | F41: =F40/F37 -> 0 | G41: =G40/G37 -> 0 | H41: =H40/H37 -> 0 | I41: =I40/I37 -> 0 | J41: =J40/J37 -> 0.22914149 | ... M41: =M40/M37 -> #DIV/0!
B43: Retained Earning | C43: =IFERROR(IF(C37>C40,1-C40,0),0) -> 0.76475478 | D43: =IFERROR(IF(D37>D40,1-D40,0),0) -> 1 | E43: =IFERROR(IF(E37>E40,1-E40,0),0) -> 1 | F43: =IFERROR(IF(F37>F40,1-F40,0),0) -> 1 | G43: =IFERROR(IF(G37>G40,1-G40,0),0) -> 1 | H43: =IFERROR(IF(H37>H40,1-H40,0),0) -> 1 | I43: =IFERROR(IF(I37>I40,1-I40,0),0) -> 1 | J43: =IFERROR(IF(J37>J40,1-J40,0),0) -> -1.3063861 | ... M43: =IFERROR(IF(M37>M40,1-M40,0),0) -> 0
B46: Balance Sheet
B47: Equity Share Capital | C47: =IFERROR('Data Sheet'!B57,0) -> 679.18 | D47: =IFERROR('Data Sheet'!C57,0) -> 679.22 | E47: =IFERROR('Data Sheet'!D57,0) -> 679.22 | F47: =IFERROR('Data Sheet'!E57,0) -> 679.22 | G47: =IFERROR('Data Sheet'!F57,0) -> 719.54 | H47: =IFERROR('Data Sheet'!G57,0) -> 765.81 | I47: =IFERROR('Data Sheet'!H57,0) -> 765.88 | J47: =IFERROR('Data Sheet'!I57,0) -> 766.02 | ... L47: =IFERROR('Data Sheet'!K57,0) -> 736
B48: Reserves | C48: =IFERROR('Data Sheet'!B58,0) -> 78273.23 | D48: =IFERROR('Data Sheet'!C58,0) -> 57382.67 | E48: =IFERROR('Data Sheet'!D58,0) -> 94748.69 | F48: =IFERROR('Data Sheet'!E58,0) -> 59500.34 | G48: =IFERROR('Data Sheet'!F58,0) -> 62358.99 | H48: =IFERROR('Data Sheet'!G58,0) -> 54480.91 | I48: =IFERROR('Data Sheet'!H58,0) -> 43795.36 | J48: =IFERROR('Data Sheet'!I58,0) -> 44555.77 | ... L48: =IFERROR('Data Sheet'!K58,0) -> 115408
B49: Borrowings | C49: =IFERROR('Data Sheet'!B59,0) -> 69359.96 | D49: =IFERROR('Data Sheet'!C59,0) -> 78603.98 | E49: =IFERROR('Data Sheet'!D59,0) -> 88950.47 | F49: =IFERROR('Data Sheet'!E59,0) -> 106175.34 | G49: =IFERROR('Data Sheet'!F59,0) -> 124787.64 | H49: =IFERROR('Data Sheet'!G59,0) -> 142130.57 | I49: =IFERROR('Data Sheet'!H59,0) -> 146449.03 | J49: =IFERROR('Data Sheet'!I59,0) -> 134113.44 | ... L49: =IFERROR('Data Sheet'!K59,0) -> 71540
B50: Other Liabilities | C50: =IFERROR('Data Sheet'!B60,0) -> 114871.75 | D50: =IFERROR('Data Sheet'!C60,0) -> 135914.49 | E50: =IFERROR('Data Sheet'!D60,0) -> 142813.43 | F50: =IFERROR('Data Sheet'!E60,0) -> 139348.59 | G50: =IFERROR('Data Sheet'!F60,0) -> 132313.22 | H50: =IFERROR('Data Sheet'!G60,0) -> 144192.62 | I50: =IFERROR('Data Sheet'!H60,0) -> 138051.22 | J50: =IFERROR('Data Sheet'!I60,0) -> 155239.2 | ... L50: =IFERROR('Data Sheet'!K60,0) -> 189289
B51: Total Liablities | C51: =IFERROR('Data Sheet'!B61,0) -> 263184.12 | D51: =IFERROR('Data Sheet'!C61,0) -> 272580.36 | E51: =IFERROR('Data Sheet'!D61,0) -> 327191.81 | F51: =IFERROR('Data Sheet'!E61,0) -> 305703.49 | G51: =IFERROR('Data Sheet'!F61,0) -> 320179.39 | H51: =IFERROR('Data Sheet'!G61,0) -> 341569.91 | I51: =IFERROR('Data Sheet'!H61,0) -> 329061.49 | J51: =IFERROR('Data Sheet'!I61,0) -> 334674.43 | ... L51: =IFERROR('Data Sheet'!K61,0) -> 376973
B54: Fix Asset Net Block | C54: =IFERROR('Data Sheet'!B62,0) -> 107231.76 | D54: =IFERROR('Data Sheet'!C62,0) -> 95944.08 | E54: =IFERROR('Data Sheet'!D62,0) -> 121413.86 | F54: =IFERROR('Data Sheet'!E62,0) -> 111234.47 | G54: =IFERROR('Data Sheet'!F62,0) -> 127107.14 | H54: =IFERROR('Data Sheet'!G62,0) -> 138707.61 | I54: =IFERROR('Data Sheet'!H62,0) -> 138855.45 | J54: =IFERROR('Data Sheet'!I62,0) -> 132079.76 | ... L54: =IFERROR('Data Sheet'!K62,0) -> 115697
B55: Capital Work in Progress | C55: =IFERROR('Data Sheet'!B63,0) -> 25918.94 | D55: =IFERROR('Data Sheet'!C63,0) -> 33698.84 | E55: =IFERROR('Data Sheet'!D63,0) -> 40033.5 | F55: =IFERROR('Data Sheet'!E63,0) -> 31883.84 | G55: =IFERROR('Data Sheet'!F63,0) -> 35622.29 | H55: =IFERROR('Data Sheet'!G63,0) -> 20963.93 | I55: =IFERROR('Data Sheet'!H63,0) -> 10251.09 | J55: =IFERROR('Data Sheet'!I63,0) -> 14274.5 | ... L55: =IFERROR('Data Sheet'!K63,0) -> 65806
B56: Investments | C56: =IFERROR('Data Sheet'!B64,0) -> 23767.02 | D56: =IFERROR('Data Sheet'!C64,0) -> 20337.92 | E56: =IFERROR('Data Sheet'!D64,0) -> 20812.75 | F56: =IFERROR('Data Sheet'!E64,0) -> 15770.72 | G56: =IFERROR('Data Sheet'!F64,0) -> 16308.48 | H56: =IFERROR('Data Sheet'!G64,0) -> 24620.28 | I56: =IFERROR('Data Sheet'!H64,0) -> 29379.53 | J56: =IFERROR('Data Sheet'!I64,0) -> 26379.16 | ... L56: =IFERROR('Data Sheet'!K64,0) -> 35656
B57: Other Assets | C57: =IFERROR('Data Sheet'!B65-SUM('Data Sheet'!B67:B69),0) -> 29579.36 | D57: =IFERROR('Data Sheet'!C65-SUM('Data Sheet'!C67:C69),0) -> 37360.78 | E57: =IFERROR('Data Sheet'!D65-SUM('Data Sheet'!D67:D69),0) -> 48286.86 | F57: =IFERROR('Data Sheet'!E65-SUM('Data Sheet'!E67:E69),0) -> 56155.74 | G57: =IFERROR('Data Sheet'!F65-SUM('Data Sheet'!F67:F69),0) -> 58784.94 | H57: =IFERROR('Data Sheet'!G65-SUM('Data Sheet'!G67:G69),0) -> 61717.96 | I57: =IFERROR('Data Sheet'!H65-SUM('Data Sheet'!H67:H69),0) -> 62223.77 | J57: =IFERROR('Data Sheet'!I65-SUM('Data Sheet'!I67:I69),0) -> 68432.09 | ... L57: =IFERROR('Data Sheet'!K65-SUM('Data Sheet'!K67:K69),0) -> 58463
B58: Total Non Current Asset | C58: =SUM(C54:C57) -> 186497.08 | D58: =SUM(D54:D57) -> 187341.62 | E58: =SUM(E54:E57) -> 230546.97 | F58: =SUM(F54:F57) -> 215044.77 | G58: =SUM(G54:G57) -> 237822.85 | H58: =SUM(H54:H57) -> 246009.78 | I58: =SUM(I54:I57) -> 240709.84 | J58: =SUM(J54:J57) -> 241165.51 | ... L58: =SUM(L54:L57) -> 275622
B61: Receivables | C61: =IFERROR('Data Sheet'!B67,0) -> 13570.91 | D61: =IFERROR('Data Sheet'!C67,0) -> 14075.55 | E61: =IFERROR('Data Sheet'!D67,0) -> 19893.3 | F61: =IFERROR('Data Sheet'!E67,0) -> 18996.17 | G61: =IFERROR('Data Sheet'!F67,0) -> 11172.69 | H61: =IFERROR('Data Sheet'!G67,0) -> 12679.08 | I61: =IFERROR('Data Sheet'!H67,0) -> 12442.12 | J61: =IFERROR('Data Sheet'!I67,0) -> 15737.97 | ... L61: =IFERROR('Data Sheet'!K67,0) -> 13248
B62: Inventory | C62: =IFERROR('Data Sheet'!B68,0) -> 32655.73 | D62: =IFERROR('Data Sheet'!C68,0) -> 35085.31 | E62: =IFERROR('Data Sheet'!D68,0) -> 42137.63 | F62: =IFERROR('Data Sheet'!E68,0) -> 39013.73 | G62: =IFERROR('Data Sheet'!F68,0) -> 37456.88 | H62: =IFERROR('Data Sheet'!G68,0) -> 36088.59 | I62: =IFERROR('Data Sheet'!H68,0) -> 35240.34 | J62: =IFERROR('Data Sheet'!I68,0) -> 40755.39 | ... L62: =IFERROR('Data Sheet'!K68,0) -> 47269
B63: Cash & Bank | C63: =IFERROR('Data Sheet'!B69,0) -> 30460.4 | D63: =IFERROR('Data Sheet'!C69,0) -> 36077.88 | E63: =IFERROR('Data Sheet'!D69,0) -> 34613.91 | F63: =IFERROR('Data Sheet'!E69,0) -> 32648.82 | G63: =IFERROR('Data Sheet'!F69,0) -> 33726.97 | H63: =IFERROR('Data Sheet'!G69,0) -> 46792.46 | I63: =IFERROR('Data Sheet'!H69,0) -> 40669.19 | J63: =IFERROR('Data Sheet'!I69,0) -> 37015.56 | ... L63: =IFERROR('Data Sheet'!K69,0) -> 40834
B64: Total Current Asset | C64: =IFERROR(SUM(C61:C63),0) -> 76687.04 | D64: =IFERROR(SUM(D61:D63),0) -> 85238.74 | E64: =IFERROR(SUM(E61:E63),0) -> 96644.84 | F64: =IFERROR(SUM(F61:F63),0) -> 90658.72 | G64: =IFERROR(SUM(G61:G63),0) -> 82356.54 | H64: =IFERROR(SUM(H61:H63),0) -> 95560.13 | I64: =IFERROR(SUM(I61:I63),0) -> 88351.65 | J64: =IFERROR(SUM(J61:J63),0) -> 93508.92 | ... L64: =IFERROR(SUM(L61:L63),0) -> 101351
B66: Total Asset | C66: =C58+C64 -> 263184.12 | D66: =D58+D64 -> 272580.36 | E66: =E58+E64 -> 327191.81 | F66: =F58+F64 -> 305703.49 | G66: =G58+G64 -> 320179.39 | H66: =H58+H64 -> 341569.91 | I66: =I58+I64 -> 329061.49 | J66: =J58+J64 -> 334674.43 | ... L66: =L58+L64 -> 376973
B68: Check | C68: =C66=C51 -> TRUE | D68: =D66=D51 -> TRUE | E68: =E66=E51 -> TRUE | F68: =F66=F51 -> TRUE | G68: =G66=G51 -> TRUE | H68: =H66=H51 -> TRUE | I68: =I66=I51 -> TRUE | J68: =J66=J51 -> TRUE | ... L68: =L66=L51 -> TRUE
A71: # | B71: Cash Flow
B72: Operating Activity -
B73: Profit from operations | C73: =IFERROR('Cash Flow Data'!C5,0) -> 38626 | D73: =IFERROR('Cash Flow Data'!D5,0) -> 28840 | E73: =IFERROR('Cash Flow Data'!E5,0) -> 33312 | F73: =IFERROR('Cash Flow Data'!F5,0) -> 28771 | G73: =IFERROR('Cash Flow Data'!G5,0) -> 23352 | H73: =IFERROR('Cash Flow Data'!H5,0) -> 31198 | I73: =IFERROR('Cash Flow Data'!I5,0) -> 26943 | J73: =IFERROR('Cash Flow Data'!J5,0) -> 41694 | ... L73: =IFERROR('Cash Flow Data'!L5,0) -> 58937
B74: Receivables | C74: =IFERROR('Cash Flow Data'!C6,0) -> -2223 | D74: =IFERROR('Cash Flow Data'!D6,0) -> -4152 | E74: =IFERROR('Cash Flow Data'!E6,0) -> -10688 | F74: =IFERROR('Cash Flow Data'!F6,0) -> -9109 | G74: =IFERROR('Cash Flow Data'!G6,0) -> 9950 | H74: =IFERROR('Cash Flow Data'!H6,0) -> -5505 | I74: =IFERROR('Cash Flow Data'!I6,0) -> 185 | J74: =IFERROR('Cash Flow Data'!J6,0) -> -2213 | ... L74: =IFERROR('Cash Flow Data'!L6,0) -> 3573
B75: Inventory | C75: =IFERROR('Cash Flow Data'!C7,0) -> -5743 | D75: =IFERROR('Cash Flow Data'!D7,0) -> -6621 | E75: =IFERROR('Cash Flow Data'!E7,0) -> -3560 | F75: =IFERROR('Cash Flow Data'!F7,0) -> 2069 | G75: =IFERROR('Cash Flow Data'!G7,0) -> 2326 | H75: =IFERROR('Cash Flow Data'!H7,0) -> 3814 | I75: =IFERROR('Cash Flow Data'!I7,0) -> 472 | J75: =IFERROR('Cash Flow Data'!J7,0) -> -5665 | ... L75: =IFERROR('Cash Flow Data'!L7,0) -> 2127
B76: Payables | C76: =IFERROR('Cash Flow Data'!C8,0) -> 3947 | D76: =IFERROR('Cash Flow Data'!D8,0) -> 9301 | E76: =IFERROR('Cash Flow Data'!E8,0) -> 7320 | F76: =IFERROR('Cash Flow Data'!F8,0) -> -4692 | G76: =IFERROR('Cash Flow Data'!G8,0) -> -8085 | H76: =IFERROR('Cash Flow Data'!H8,0) -> 5748 | I76: =IFERROR('Cash Flow Data'!I8,0) -> -7012 | J76: =IFERROR('Cash Flow Data'!J8,0) -> 6945 | ... L76: =IFERROR('Cash Flow Data'!L8,0) -> 1303
B77: Loans Advances | C77: =IFERROR('Cash Flow Data'!C9,0) -> -520 | D77: =IFERROR('Cash Flow Data'!D9,0) -> 0 | E77: =IFERROR('Cash Flow Data'!E9,0) -> 0 | F77: =IFERROR('Cash Flow Data'!F9,0) -> 0 | G77: =IFERROR('Cash Flow Data'!G9,0) -> 0 | H77: =IFERROR('Cash Flow Data'!H9,0) -> 0 | I77: =IFERROR('Cash Flow Data'!I9,0) -> 0 | J77: =IFERROR('Cash Flow Data'!J9,0) -> 0 | ... L77: =IFERROR('Cash Flow Data'!L9,0) -> 0
B78: Other WC items | C78: =IFERROR('Cash Flow Data'!C10,0) -> 5852 | D78: =IFERROR('Cash Flow Data'!D10,0) -> 4727 | E78: =IFERROR('Cash Flow Data'!E10,0) -> 494 | F78: =IFERROR('Cash Flow Data'!F10,0) -> 4512 | G78: =IFERROR('Cash Flow Data'!G10,0) -> 875 | H78: =IFERROR('Cash Flow Data'!H10,0) -> -4150 | I78: =IFERROR('Cash Flow Data'!I10,0) -> -4396 | J78: =IFERROR('Cash Flow Data'!J10,0) -> -2194 | ... L78: =IFERROR('Cash Flow Data'!L10,0) -> 1153
B79: Working capital changes | C79: =IFERROR('Cash Flow Data'!C11,0) -> 1313 | D79: =IFERROR('Cash Flow Data'!D11,0) -> 3254 | E79: =IFERROR('Cash Flow Data'!E11,0) -> -6434 | F79: =IFERROR('Cash Flow Data'!F11,0) -> -7221 | G79: =IFERROR('Cash Flow Data'!G11,0) -> 5065 | H79: =IFERROR('Cash Flow Data'!H11,0) -> -93 | I79: =IFERROR('Cash Flow Data'!I11,0) -> -10750 | J79: =IFERROR('Cash Flow Data'!J11,0) -> -3127 | ... L79: =IFERROR('Cash Flow Data'!L11,0) -> 8156
B80: Direct taxes | C80: =IFERROR('Cash Flow Data'!C12,0) -> -2040 | D80: =IFERROR('Cash Flow Data'!D12,0) -> -1895 | E80: =IFERROR('Cash Flow Data'!E12,0) -> -3021 | F80: =IFERROR('Cash Flow Data'!F12,0) -> -2659 | G80: =IFERROR('Cash Flow Data'!G12,0) -> -1785 | H80: =IFERROR('Cash Flow Data'!H12,0) -> -2105 | I80: =IFERROR('Cash Flow Data'!I12,0) -> -1910 | J80: =IFERROR('Cash Flow Data'!J12,0) -> -3179 | ... L80: =IFERROR('Cash Flow Data'!L12,0) -> -3991
B81: Cash from Operating Activity - | C81: =C73+C79+C80 -> 37899 | D81: =D73+D79+D80 -> 30199 | E81: =E73+E79+E80 -> 23857 | F81: =F73+F79+F80 -> 18891 | G81: =G73+G79+G80 -> 26632 | H81: =H73+H79+H80 -> 29000 | I81: =I73+I79+I80 -> 14283 | J81: =J73+J79+J80 -> 35388 | ... L81: =L73+L79+L80 -> 63102
B83: Investing Activity -
B84: Fixed assets purchased | C84: =IFERROR('Cash Flow Data'!C14,0) -> -31503 | D84: =IFERROR('Cash Flow Data'!D14,0) -> -16072 | E84: =IFERROR('Cash Flow Data'!E14,0) -> -35079 | F84: =IFERROR('Cash Flow Data'!F14,0) -> -35304 | G84: =IFERROR('Cash Flow Data'!G14,0) -> -29702 | H84: =IFERROR('Cash Flow Data'!H14,0) -> -20205 | I84: =IFERROR('Cash Flow Data'!I14,0) -> -15168 | J84: =IFERROR('Cash Flow Data'!J14,0) -> -19230 | ... L84: =IFERROR('Cash Flow Data'!L14,0) -> -38042
B85: Fixed assets sold | C85: =IFERROR('Cash Flow Data'!C15,0) -> 59 | D85: =IFERROR('Cash Flow Data'!D15,0) -> 53 | E85: =IFERROR('Cash Flow Data'!E15,0) -> 30 | F85: =IFERROR('Cash Flow Data'!F15,0) -> 67 | G85: =IFERROR('Cash Flow Data'!G15,0) -> 171 | H85: =IFERROR('Cash Flow Data'!H15,0) -> 351 | I85: =IFERROR('Cash Flow Data'!I15,0) -> 230 | J85: =IFERROR('Cash Flow Data'!J15,0) -> 285 | ... L85: =IFERROR('Cash Flow Data'!L15,0) -> 974
B86: Investments purchased | C86: =IFERROR('Cash Flow Data'!C16,0) -> -4728 | D86: =IFERROR('Cash Flow Data'!D16,0) -> -6 | E86: =IFERROR('Cash Flow Data'!E16,0) -> -329 | F86: =IFERROR('Cash Flow Data'!F16,0) -> -130 | G86: =IFERROR('Cash Flow Data'!G16,0) -> -1439 | H86: =IFERROR('Cash Flow Data'!H16,0) -> -7530 | I86: =IFERROR('Cash Flow Data'!I16,0) -> -3008 | J86: =IFERROR('Cash Flow Data'!J16,0) -> -50 | ... L86: =IFERROR('Cash Flow Data'!L16,0) -> -12677
B87: Investments sold | C87: =IFERROR('Cash Flow Data'!C17,0) -> 89 | D87: =IFERROR('Cash Flow Data'!D17,0) -> 1965 | E87: =IFERROR('Cash Flow Data'!E17,0) -> 2381 | F87: =IFERROR('Cash Flow Data'!F17,0) -> 5644 | G87: =IFERROR('Cash Flow Data'!G17,0) -> 21 | H87: =IFERROR('Cash Flow Data'!H17,0) -> 226 | I87: =IFERROR('Cash Flow Data'!I17,0) -> 104 | J87: =IFERROR('Cash Flow Data'!J17,0) -> 6895 | ... L87: =IFERROR('Cash Flow Data'!L17,0) -> 111
B88: Interest received | C88: =IFERROR('Cash Flow Data'!C18,0) -> 731 | D88: =IFERROR('Cash Flow Data'!D18,0) -> 638 | E88: =IFERROR('Cash Flow Data'!E18,0) -> 690 | F88: =IFERROR('Cash Flow Data'!F18,0) -> 761 | G88: =IFERROR('Cash Flow Data'!G18,0) -> 1104 | H88: =IFERROR('Cash Flow Data'!H18,0) -> 428 | I88: =IFERROR('Cash Flow Data'!I18,0) -> 653 | J88: =IFERROR('Cash Flow Data'!J18,0) -> 973 | ... L88: =IFERROR('Cash Flow Data'!L18,0) -> 2420
B89: Dividends received | C89: =IFERROR('Cash Flow Data'!C19,0) -> 58 | D89: =IFERROR('Cash Flow Data'!D19,0) -> 620 | E89: =IFERROR('Cash Flow Data'!E19,0) -> 1797 | F89: =IFERROR('Cash Flow Data'!F19,0) -> 232 | G89: =IFERROR('Cash Flow Data'!G19,0) -> 21 | H89: =IFERROR('Cash Flow Data'!H19,0) -> 18 | I89: =IFERROR('Cash Flow Data'!I19,0) -> 32 | J89: =IFERROR('Cash Flow Data'!J19,0) -> 46 | ... L89: =IFERROR('Cash Flow Data'!L19,0) -> 64
B90: Investment in group cos | C90: =IFERROR('Cash Flow Data'!C20,0) -> 0 | D90: =IFERROR('Cash Flow Data'!D20,0) -> -107 | E90: =IFERROR('Cash Flow Data'!E20,0) -> -4 | F90: =IFERROR('Cash Flow Data'!F20,0) -> -9 | G90: =IFERROR('Cash Flow Data'!G20,0) -> -606 | H90: =IFERROR('Cash Flow Data'!H20,0) -> -10 | I90: =IFERROR('Cash Flow Data'!I20,0) -> 0 | J90: =IFERROR('Cash Flow Data'!J20,0) -> 0 | ... L90: =IFERROR('Cash Flow Data'!L20,0) -> 0
B91: Redemp n Canc of Shares | C91: =IFERROR('Cash Flow Data'!C21,0) -> 0 | D91: =IFERROR('Cash Flow Data'!D21,0) -> 0 | E91: =IFERROR('Cash Flow Data'!E21,0) -> 14 | F91: =IFERROR('Cash Flow Data'!F21,0) -> 533 | G91: =IFERROR('Cash Flow Data'!G21,0) -> 0 | H91: =IFERROR('Cash Flow Data'!H21,0) -> 0 | I91: =IFERROR('Cash Flow Data'!I21,0) -> 0 | J91: =IFERROR('Cash Flow Data'!J21,0) -> 19 | ... L91: =IFERROR('Cash Flow Data'!L21,0) -> 765
B92: Acquisition of companies | C92: =IFERROR('Cash Flow Data'!C22,0) -> -111 | D92: =IFERROR('Cash Flow Data'!D22,0) -> 0 | E92: =IFERROR('Cash Flow Data'!E22,0) -> 0 | F92: =IFERROR('Cash Flow Data'!F22,0) -> -8 | G92: =IFERROR('Cash Flow Data'!G22,0) -> -27 | H92: =IFERROR('Cash Flow Data'!H22,0) -> 0 | I92: =IFERROR('Cash Flow Data'!I22,0) -> -98 | J92: =IFERROR('Cash Flow Data'!J22,0) -> 0 | ... L92: =IFERROR('Cash Flow Data'!L22,0) -> -688
B93: Inter corporate deposits | C93: =IFERROR('Cash Flow Data'!C23,0) -> 0 | D93: =IFERROR('Cash Flow Data'!D23,0) -> 0 | E93: =IFERROR('Cash Flow Data'!E23,0) -> 0 | F93: =IFERROR('Cash Flow Data'!F23,0) -> 0 | G93: =IFERROR('Cash Flow Data'!G23,0) -> 0 | H93: =IFERROR('Cash Flow Data'!H23,0) -> 0 | I93: =IFERROR('Cash Flow Data'!I23,0) -> 0 | J93: =IFERROR('Cash Flow Data'!J23,0) -> 0 | ... L93: =IFERROR('Cash Flow Data'!L23,0) -> -20
B94: Other investing items | C94: =IFERROR('Cash Flow Data'!C24,0) -> -1289 | D94: =IFERROR('Cash Flow Data'!D24,0) -> -26663 | E94: =IFERROR('Cash Flow Data'!E24,0) -> 5360 | F94: =IFERROR('Cash Flow Data'!F24,0) -> 7335 | G94: =IFERROR('Cash Flow Data'!G24,0) -> -2659 | H94: =IFERROR('Cash Flow Data'!H24,0) -> 1051 | I94: =IFERROR('Cash Flow Data'!I24,0) -> 12813 | J94: =IFERROR('Cash Flow Data'!J24,0) -> -4357 | ... L94: =IFERROR('Cash Flow Data'!L24,0) -> -2889
B95: Cash from Investing Activity - | C95: =SUM(C84:C94) -> -36694 | D95: =SUM(D84:D94) -> -39572 | E95: =SUM(E84:E94) -> -25140 | F95: =SUM(F84:F94) -> -20879 | G95: =SUM(G84:G94) -> -33116 | H95: =SUM(H84:H94) -> -25671 | I95: =SUM(I84:I94) -> -4442 | J95: =SUM(J84:J94) -> -15419 | ... L95: =SUM(L84:L94) -> -49982
B97: Financing Activity -
B98: Proceeds from shares | C98: =IFERROR('Cash Flow Data'!C26,0) -> 7433 | D98: =IFERROR('Cash Flow Data'!D26,0) -> 5 | E98: =IFERROR('Cash Flow Data'!E26,0) -> 0 | F98: =IFERROR('Cash Flow Data'!F26,0) -> 0 | G98: =IFERROR('Cash Flow Data'!G26,0) -> 3889 | H98: =IFERROR('Cash Flow Data'!H26,0) -> 2603 | I98: =IFERROR('Cash Flow Data'!I26,0) -> 19 | J98: =IFERROR('Cash Flow Data'!J26,0) -> 20 | ... L98: =IFERROR('Cash Flow Data'!L26,0) -> 1108
B99: Redemption of debentures | C99: =IFERROR('Cash Flow Data'!C27,0) -> 0 | D99: =IFERROR('Cash Flow Data'!D27,0) -> 0 | E99: =IFERROR('Cash Flow Data'!E27,0) -> 0 | F99: =IFERROR('Cash Flow Data'!F27,0) -> 0 | G99: =IFERROR('Cash Flow Data'!G27,0) -> 0 | H99: =IFERROR('Cash Flow Data'!H27,0) -> 0 | I99: =IFERROR('Cash Flow Data'!I27,0) -> 0 | J99: =IFERROR('Cash Flow Data'!J27,0) -> 0 | ... L99: =IFERROR('Cash Flow Data'!L27,0) -> 0
B100: Proceeds from borrowings | C100: =IFERROR('Cash Flow Data'!C28,0) -> 19519 | D100: =IFERROR('Cash Flow Data'!D28,0) -> 33390 | E100: =IFERROR('Cash Flow Data'!E28,0) -> 37482 | F100: =IFERROR('Cash Flow Data'!F28,0) -> 51128 | G100: =IFERROR('Cash Flow Data'!G28,0) -> 38297 | H100: =IFERROR('Cash Flow Data'!H28,0) -> 46641 | I100: =IFERROR('Cash Flow Data'!I28,0) -> 46578 | J100: =IFERROR('Cash Flow Data'!J28,0) -> 43934 | ... L100: =IFERROR('Cash Flow Data'!L28,0) -> 13384
B101: Repayment of borrowings | C101: =IFERROR('Cash Flow Data'!C29,0) -> -24924 | D101: =IFERROR('Cash Flow Data'!D29,0) -> -21732 | E101: =IFERROR('Cash Flow Data'!E29,0) -> -29964 | F101: =IFERROR('Cash Flow Data'!F29,0) -> -35198 | G101: =IFERROR('Cash Flow Data'!G29,0) -> -29847 | H101: =IFERROR('Cash Flow Data'!H29,0) -> -29709 | I101: =IFERROR('Cash Flow Data'!I29,0) -> -42816 | J101: =IFERROR('Cash Flow Data'!J29,0) -> -62557 | ... L101: =IFERROR('Cash Flow Data'!L29,0) -> -21443
B102: Interest paid fin | C102: =IFERROR('Cash Flow Data'!C30,0) -> -5716 | D102: =IFERROR('Cash Flow Data'!D30,0) -> -5336 | E102: =IFERROR('Cash Flow Data'!E30,0) -> -5411 | F102: =IFERROR('Cash Flow Data'!F30,0) -> -7005 | G102: =IFERROR('Cash Flow Data'!G30,0) -> -7518 | H102: =IFERROR('Cash Flow Data'!H30,0) -> -8123 | I102: =IFERROR('Cash Flow Data'!I30,0) -> -9251 | J102: =IFERROR('Cash Flow Data'!J30,0) -> -9336 | ... L102: =IFERROR('Cash Flow Data'!L30,0) -> -5814
B103: Dividends paid | C103: =IFERROR('Cash Flow Data'!C31,0) -> -108 | D103: =IFERROR('Cash Flow Data'!D31,0) -> -121 | E103: =IFERROR('Cash Flow Data'!E31,0) -> -96 | F103: =IFERROR('Cash Flow Data'!F31,0) -> -95 | G103: =IFERROR('Cash Flow Data'!G31,0) -> -57 | H103: =IFERROR('Cash Flow Data'!H31,0) -> -30 | I103: =IFERROR('Cash Flow Data'!I31,0) -> -100 | J103: =IFERROR('Cash Flow Data'!J31,0) -> -141 | ... L103: =IFERROR('Cash Flow Data'!L31,0) -> -2492
B104: Financial liabilities | C104: =IFERROR('Cash Flow Data'!C32,0) -> 0 | D104: =IFERROR('Cash Flow Data'!D32,0) -> 0 | E104: =IFERROR('Cash Flow Data'!E32,0) -> 0 | F104: =IFERROR('Cash Flow Data'!F32,0) -> 0 | G104: =IFERROR('Cash Flow Data'!G32,0) -> -1346 | H104: =IFERROR('Cash Flow Data'!H32,0) -> -1477 | I104: =IFERROR('Cash Flow Data'!I32,0) -> -1559 | J104: =IFERROR('Cash Flow Data'!J32,0) -> -1517 | ... L104: =IFERROR('Cash Flow Data'!L32,0) -> -2393
B105: Other financing items | C105: =IFERROR('Cash Flow Data'!C33,0) -> 0 | D105: =IFERROR('Cash Flow Data'!D33,0) -> 0 | E105: =IFERROR('Cash Flow Data'!E33,0) -> 0 | F105: =IFERROR('Cash Flow Data'!F33,0) -> 0 | G105: =IFERROR('Cash Flow Data'!G33,0) -> -29 | H105: =IFERROR('Cash Flow Data'!H33,0) -> 0 | I105: =IFERROR('Cash Flow Data'!I33,0) -> 3750 | J105: =IFERROR('Cash Flow Data'!J33,0) -> 3355 | ... L105: =IFERROR('Cash Flow Data'!L33,0) -> -1136
B106: Cash from Financing Activity - | C106: =SUM(C98:C105) -> -3796 | D106: =SUM(D98:D105) -> 6206 | E106: =SUM(E98:E105) -> 2011 | F106: =SUM(F98:F105) -> 8830 | G106: =SUM(G98:G105) -> 3389 | H106: =SUM(H98:H105) -> 9905 | I106: =SUM(I98:I105) -> -3379 | J106: =SUM(J98:J105) -> -26242 | ... L106: =SUM(L98:L105) -> -18786
B108: Net Cash Flow | C108: =C81+C106+C95 -> -2591 | D108: =D81+D106+D95 -> -3167 | E108: =E81+E106+E95 -> 728 | F108: =F81+F106+F95 -> 6842 | G108: =G81+G106+G95 -> -3095 | H108: =H81+H106+H95 -> 13234 | I108: =I81+I106+I95 -> 6462 | J108: =J81+J106+J95 -> -6273 | ... L108: =L81+L106+L95 -> -5666

Sheet Common Size Statement
B2: ="Common Size"&" "&"-"&'Data Sheet'!B1 -> Common Size -TATA MOTORS LTD
B4: Particular | C4: ='Data Sheet'!B56 -> 42460 | D4: ='Data Sheet'!C56 -> 42825 | E4: ='Data Sheet'!D56 -> 43190 | F4: ='Data Sheet'!E56 -> 43555 | G4: ='Data Sheet'!F56 -> 43921 | H4: ='Data Sheet'!G56 -> 44286 | I4: ='Data Sheet'!H56 -> 44651 | J4: ='Data Sheet'!I56 -> 45016 | ... L4: ='Data Sheet'!K56 -> 45747
B5: ='Data Sheet'!A17 -> Sales | C5: ='Data Sheet'!B17/'Data Sheet'!B$17 -> 1 | D5: ='Data Sheet'!C17/'Data Sheet'!C$17 -> 1 | E5: ='Data Sheet'!D17/'Data Sheet'!D$17 -> 1 | F5: ='Data Sheet'!E17/'Data Sheet'!E$17 -> 1 | G5: ='Data Sheet'!F17/'Data Sheet'!F$17 -> 1 | H5: ='Data Sheet'!G17/'Data Sheet'!G$17 -> 1 | I5: ='Data Sheet'!H17/'Data Sheet'!H$17 -> 1 | J5: ='Data Sheet'!I17/'Data Sheet'!I$17 -> 1 | ... L5: ='Data Sheet'!K17/'Data Sheet'!K$17 -> 1
B6: ='Data Sheet'!A18 -> Raw Material Cost | C6: ='Data Sheet'!B18/'Data Sheet'!B$17 -> 0.60844786 | D6: ='Data Sheet'!C18/'Data Sheet'!C$17 -> 0.64256171 | E6: ='Data Sheet'!D18/'Data Sheet'!D$17 -> 0.64447357 | F6: ='Data Sheet'!E18/'Data Sheet'!E$17 -> 0.64340246 | G6: ='Data Sheet'!F18/'Data Sheet'!F$17 -> 0.63163559 | H6: ='Data Sheet'!G18/'Data Sheet'!G$17 -> 0.6149343 | I6: ='Data Sheet'!H18/'Data Sheet'!H$17 -> 0.64389657 | J6: ='Data Sheet'!I18/'Data Sheet'!I$17 -> 0.66842005 | ... L6: ='Data Sheet'!K18/'Data Sheet'!K$17 -> 0.611674
B7: ='Data Sheet'!A19 -> Change in Inventory | C7: ='Data Sheet'!B19/'Data Sheet'!B$17 -> 0.010075204 | D7: ='Data Sheet'!C19/'Data Sheet'!C$17 -> 0.027438359 | E7: ='Data Sheet'!D19/'Data Sheet'!D$17 -> 0.007019642 | F7: ='Data Sheet'!E19/'Data Sheet'!E$17 -> -0.0068003275 | G7: ='Data Sheet'!F19/'Data Sheet'!F$17 -> -0.008546395 | H7: ='Data Sheet'!G19/'Data Sheet'!G$17 -> -0.018752035 | I7: ='Data Sheet'!H19/'Data Sheet'!H$17 -> -0.0057118668 | J7: ='Data Sheet'!I19/'Data Sheet'!I$17 -> 0.01382103 | ... L7: ='Data Sheet'!K19/'Data Sheet'!K$17 -> -0.0064499255
B8: ='Data Sheet'!A20 -> Power and Fuel | C8: ='Data Sheet'!B20/'Data Sheet'!B$17 -> 0.0041884213 | D8: ='Data Sheet'!C20/'Data Sheet'!C$17 -> 0.0043005273 | E8: ='Data Sheet'!D20/'Data Sheet'!D$17 -> 0.004486633 | F8: ='Data Sheet'!E20/'Data Sheet'!E$17 -> 0.0052524952 | G8: ='Data Sheet'!F20/'Data Sheet'!F$17 -> 0.0048452899 | H8: ='Data Sheet'!G20/'Data Sheet'!G$17 -> 0.0044551377 | I8: ='Data Sheet'!H20/'Data Sheet'!H$17 -> 0.0078228109 | J8: ='Data Sheet'!I20/'Data Sheet'!I$17 -> 0.007264653 | ... L8: ='Data Sheet'!K20/'Data Sheet'!K$17 -> 0.0055561241
B9: ='Data Sheet'!A21 -> Other Mfr. Exp | C9: ='Data Sheet'!B21/'Data Sheet'!B$17 -> 0.044320546 | D9: ='Data Sheet'!C21/'Data Sheet'!C$17 -> 0.037329068 | E9: ='Data Sheet'!D21/'Data Sheet'!D$17 -> 0.037632111 | F9: ='Data Sheet'!E21/'Data Sheet'!E$17 -> 0.038731543 | G9: ='Data Sheet'!F21/'Data Sheet'!F$17 -> 0.044208832 | H9: ='Data Sheet'!G21/'Data Sheet'!G$17 -> 0.033119871 | I9: ='Data Sheet'!H21/'Data Sheet'!H$17 -> 0.033856195 | J9: ='Data Sheet'!I21/'Data Sheet'!I$17 -> 0.03400894 | ... L9: ='Data Sheet'!K21/'Data Sheet'!K$17 -> 0.042786477
B10: ='Data Sheet'!A22 -> Employee Cost | C10: ='Data Sheet'!B22/'Data Sheet'!B$17 -> 0.10577314 | D10: ='Data Sheet'!C22/'Data Sheet'!C$17 -> 0.10505627 | E10: ='Data Sheet'!D22/'Data Sheet'!D$17 -> 0.10392742 | F10: ='Data Sheet'!E22/'Data Sheet'!E$17 -> 0.1101015 | G10: ='Data Sheet'!F22/'Data Sheet'!F$17 -> 0.11659263 | H10: ='Data Sheet'!G22/'Data Sheet'!G$17 -> 0.11068479 | I10: ='Data Sheet'!H22/'Data Sheet'!H$17 -> 0.11064148 | J10: ='Data Sheet'!I22/'Data Sheet'!I$17 -> 0.097277205 | ... L10: ='Data Sheet'!K22/'Data Sheet'!K$17 -> 0.10863667
B11: ='Data Sheet'!A23 -> Selling and admin | C11: ='Data Sheet'!B23/'Data Sheet'!B$17 -> 0.080542957 | D11: ='Data Sheet'!C23/'Data Sheet'!C$17 -> 0.11138381 | E11: ='Data Sheet'!D23/'Data Sheet'!D$17 -> 0.10634378 | F11: ='Data Sheet'!E23/'Data Sheet'!E$17 -> 0.10836581 | G11: ='Data Sheet'!F23/'Data Sheet'!F$17 -> 0.11203335 | H11: ='Data Sheet'!G23/'Data Sheet'!G$17 -> 0.092138806 | I11: ='Data Sheet'!H23/'Data Sheet'!H$17 -> 0.10488425 | J11: ='Data Sheet'!I23/'Data Sheet'!I$17 -> 0.10070091 | ... L11: ='Data Sheet'!K23/'Data Sheet'!K$17 -> 0.10711743
B12: ='Data Sheet'!A24 -> Other Expenses | C12: ='Data Sheet'!B24/'Data Sheet'!B$17 -> 0.026183832 | D12: ='Data Sheet'!C24/'Data Sheet'!C$17 -> 0.017094283 | E12: ='Data Sheet'!D24/'Data Sheet'!D$17 -> 0.0022582367 | F12: ='Data Sheet'!E24/'Data Sheet'!E$17 -> 0.0056592338 | G12: ='Data Sheet'!F24/'Data Sheet'!F$17 -> 0.013239885 | H12: ='Data Sheet'!G24/'Data Sheet'!G$17 -> -0.0033407828 | I12: ='Data Sheet'!H24/'Data Sheet'!H$17 -> 0.0044105011 | J12: ='Data Sheet'!I24/'Data Sheet'!I$17 -> 0.014187308 | ... L12: ='Data Sheet'!K24/'Data Sheet'!K$17 -> -0.0077985877
B13: ='Data Sheet'!A25 -> Other Income | C13: ='Data Sheet'!B25/'Data Sheet'!B$17 -> -0.0097771947 | D13: ='Data Sheet'!C25/'Data Sheet'!C$17 -> 0.0069304854 | E13: ='Data Sheet'!D25/'Data Sheet'!D$17 -> 0.020348895 | F13: ='Data Sheet'!E25/'Data Sheet'!E$17 -> -0.088383094 | G13: ='Data Sheet'!F25/'Data Sheet'!F$17 -> 0.00038959203 | H13: ='Data Sheet'!G25/'Data Sheet'!G$17 -> -0.044507861 | I13: ='Data Sheet'!H25/'Data Sheet'!H$17 -> 0.0087053995 | J13: ='Data Sheet'!I25/'Data Sheet'!I$17 -> 0.019261868 | ... L13: ='Data Sheet'!K25/'Data Sheet'!K$17 -> 0.026777653
B14: ='Data Sheet'!A26 -> Depreciation | C14: ='Data Sheet'!B26/'Data Sheet'!B$17 -> 0.061201426 | D14: ='Data Sheet'!C26/'Data Sheet'!C$17 -> 0.066390387 | E14: ='Data Sheet'!D26/'Data Sheet'!D$17 -> 0.073927472 | F14: ='Data Sheet'!E26/'Data Sheet'!E$17 -> 0.078130605 | G14: ='Data Sheet'!F26/'Data Sheet'!F$17 -> 0.082068398 | H14: ='Data Sheet'!G26/'Data Sheet'!G$17 -> 0.094264231 | I14: ='Data Sheet'!H26/'Data Sheet'!H$17 -> 0.089191478 | J14: ='Data Sheet'!I26/'Data Sheet'!I$17 -> 0.071857611 | ... L14: ='Data Sheet'!K26/'Data Sheet'!K$17 -> 0.052891209
B15: ='Data Sheet'!A27 -> Interest | C15: ='Data Sheet'!B27/'Data Sheet'!B$17 -> 0.017905727 | D15: ='Data Sheet'!C27/'Data Sheet'!C$17 -> 0.01571423 | E15: ='Data Sheet'!D27/'Data Sheet'!D$17 -> 0.016058248 | F15: ='Data Sheet'!E27/'Data Sheet'!E$17 -> 0.019072102 | G15: ='Data Sheet'!F27/'Data Sheet'!F$17 -> 0.027744997 | H15: ='Data Sheet'!G27/'Data Sheet'!G$17 -> 0.032415293 | I15: ='Data Sheet'!H27/'Data Sheet'!H$17 -> 0.033441332 | J15: ='Data Sheet'!I27/'Data Sheet'!I$17 -> 0.029556232 | ... L15: ='Data Sheet'!K27/'Data Sheet'!K$17 -> 0.011560286
B16: ='Data Sheet'!A28 -> Profit before tax | C16: ='Data Sheet'!B28/'Data Sheet'!B$17 -> 0.051734106 | D16: ='Data Sheet'!C28/'Data Sheet'!C$17 -> 0.034538557 | E16: ='Data Sheet'!D28/'Data Sheet'!D$17 -> 0.038261059 | F16: ='Data Sheet'!E28/'Data Sheet'!E$17 -> -0.10389917 | G16: ='Data Sheet'!F28/'Data Sheet'!F$17 -> -0.040525768 | H16: ='Data Sheet'!G28/'Data Sheet'!G$17 -> -0.041931546 | I16: ='Data Sheet'!H28/'Data Sheet'!H$17 -> -0.025151083 | J16: ='Data Sheet'!I28/'Data Sheet'!I$17 -> 0.0098099827 | ... L16: ='Data Sheet'!K28/'Data Sheet'!K$17 -> 0.087904115
... B20: ='Data Sheet'!A32 -> EBITDA | C20: ='Data Sheet'!B32/'Data Sheet'!B$17 -> 0.13259404 | D20: ='Data Sheet'!C32/'Data Sheet'!C$17 -> 0.12180016 | E20: ='Data Sheet'!D32/'Data Sheet'!D$17 -> 0.13570967 | F20: ='Data Sheet'!E32/'Data Sheet'!E$17 -> -0.0063405317 | G20: ='Data Sheet'!F32/'Data Sheet'!F$17 -> 0.065090942 | H20: ='Data Sheet'!G32/'Data Sheet'!G$17 -> 0.083005548 | I20: ='Data Sheet'!H32/'Data Sheet'!H$17 -> 0.096739163 | J20: ='Data Sheet'!I32/'Data Sheet'!I$17 -> 0.11042728 | ... L20: ='Data Sheet'!K32/'Data Sheet'!K$17 -> 0.15163011
B22: ="Common Size Statement Balance Sheet"&" "&"-"&'Data Sheet'!B1 -> Common Size Statement Balance Sheet -TATA MOTORS LTD
B24: Particular | C24: ='Data Sheet'!B56 -> 42460 | D24: ='Data Sheet'!C56 -> 42825 | E24: ='Data Sheet'!D56 -> 43190 | F24: ='Data Sheet'!E56 -> 43555 | G24: ='Data Sheet'!F56 -> 43921 | H24: ='Data Sheet'!G56 -> 44286 | I24: ='Data Sheet'!H56 -> 44651 | J24: ='Data Sheet'!I56 -> 45016 | ... L24: ='Data Sheet'!K56 -> 45747
B25: ='Data Sheet'!A57 -> Equity Share Capital | C25: ='Data Sheet'!B57/'Data Sheet'!B$61 -> 0.0025806268 | D25: ='Data Sheet'!C57/'Data Sheet'!C$61 -> 0.0024918156 | E25: ='Data Sheet'!D57/'Data Sheet'!D$61 -> 0.0020759077 | F25: ='Data Sheet'!E57/'Data Sheet'!E$61 -> 0.0022218261 | G25: ='Data Sheet'!F57/'Data Sheet'!F$61 -> 0.0022473027 | H25: ='Data Sheet'!G57/'Data Sheet'!G$61 -> 0.00224203 | I25: ='Data Sheet'!H57/'Data Sheet'!H$61 -> 0.0023274677 | J25: ='Data Sheet'!I57/'Data Sheet'!I$61 -> 0.0022888513 | ... L25: ='Data Sheet'!K57/'Data Sheet'!K$61 -> 0.0019523945
B26: ='Data Sheet'!A58 -> Reserves | C26: ='Data Sheet'!B58/'Data Sheet'!B$61 -> 0.29740864 | D26: ='Data Sheet'!C58/'Data Sheet'!C$61 -> 0.21051652 | E26: ='Data Sheet'!D58/'Data Sheet'!D$61 -> 0.28958148 | F26: ='Data Sheet'!E58/'Data Sheet'!E$61 -> 0.19463415 | G26: ='Data Sheet'!F58/'Data Sheet'!F$61 -> 0.19476266 | H26: ='Data Sheet'!G58/'Data Sheet'!G$61 -> 0.15950149 | I26: ='Data Sheet'!H58/'Data Sheet'!H$61 -> 0.13309172 | J26: ='Data Sheet'!I58/'Data Sheet'!I$61 -> 0.13313168 | ... L26: ='Data Sheet'!K58/'Data Sheet'!K$61 -> 0.30614394
B27: ='Data Sheet'!A59 -> Borrowings | C27: ='Data Sheet'!B59/'Data Sheet'!B$61 -> 0.26354158 | D27: ='Data Sheet'!C59/'Data Sheet'!C$61 -> 0.28836993 | E27: ='Data Sheet'!D59/'Data Sheet'!D$61 -> 0.27186032 | F27: ='Data Sheet'!E59/'Data Sheet'!E$61 -> 0.34731478 | G27: ='Data Sheet'!F59/'Data Sheet'!F$61 -> 0.38974289 | H27: ='Data Sheet'!G59/'Data Sheet'!G$61 -> 0.41610975 | I27: ='Data Sheet'!H59/'Data Sheet'!H$61 -> 0.44505065 | J27: ='Data Sheet'!I59/'Data Sheet'!I$61 -> 0.40072807 | ... L27: ='Data Sheet'!K59/'Data Sheet'!K$61 -> 0.18977486
B28: ='Data Sheet'!A60 -> Other Liabilities | C28: ='Data Sheet'!B60/'Data Sheet'!B$61 -> 0.43646915 | D28: ='Data Sheet'!C60/'Data Sheet'!C$61 -> 0.49862173 | E28: ='Data Sheet'!D60/'Data Sheet'!D$61 -> 0.43648229 | F28: ='Data Sheet'!E60/'Data Sheet'!E$61 -> 0.45582924 | G28: ='Data Sheet'!F60/'Data Sheet'!F$61 -> 0.41324715 | H28: ='Data Sheet'!G60/'Data Sheet'!G$61 -> 0.42214673 | I28: ='Data Sheet'!H60/'Data Sheet'!H$61 -> 0.41953016 | J28: ='Data Sheet'!I60/'Data Sheet'!I$61 -> 0.46385139 | ... L28: ='Data Sheet'!K60/'Data Sheet'!K$61 -> 0.5021288
B29: ='Data Sheet'!A61 -> Total | C29: ='Data Sheet'!B61/'Data Sheet'!B$61 -> 1 | D29: ='Data Sheet'!C61/'Data Sheet'!C$61 -> 1 | E29: ='Data Sheet'!D61/'Data Sheet'!D$61 -> 1 | F29: ='Data Sheet'!E61/'Data Sheet'!E$61 -> 1 | G29: ='Data Sheet'!F61/'Data Sheet'!F$61 -> 1 | H29: ='Data Sheet'!G61/'Data Sheet'!G$61 -> 1 | I29: ='Data Sheet'!H61/'Data Sheet'!H$61 -> 1 | J29: ='Data Sheet'!I61/'Data Sheet'!I$61 -> 1 | ... L29: ='Data Sheet'!K61/'Data Sheet'!K$61 -> 1
B31: ='Data Sheet'!A62 -> Net Block | C31: ='Data Sheet'!B62/'Data Sheet'!B$75 -> 0.40744008 | D31: ='Data Sheet'!C62/'Data Sheet'!C$75 -> 0.35198457 | E31: ='Data Sheet'!D62/'Data Sheet'!D$75 -> 0.37107854 | F31: ='Data Sheet'!E62/'Data Sheet'!E$75 -> 0.36386392 | G31: ='Data Sheet'!F62/'Data Sheet'!F$75 -> 0.39698726 | H31: ='Data Sheet'!G62/'Data Sheet'!G$75 -> 0.40608849 | I31: ='Data Sheet'!H62/'Data Sheet'!H$75 -> 0.42197417 | J31: ='Data Sheet'!I62/'Data Sheet'!I$75 -> 0.39465148 | ... L31: ='Data Sheet'!K62/'Data Sheet'!K$75 -> 0.30691057
B32: ='Data Sheet'!A63 -> Capital Work in Progress | C32: ='Data Sheet'!B63/'Data Sheet'!B$75 -> 0.098482158 | D32: ='Data Sheet'!C63/'Data Sheet'!C$75 -> 0.12362901 | E32: ='Data Sheet'!D63/'Data Sheet'!D$75 -> 0.12235484 | F32: ='Data Sheet'!E63/'Data Sheet'!E$75 -> 0.10429662 | G32: ='Data Sheet'!F63/'Data Sheet'!F$75 -> 0.11125729 | H32: ='Data Sheet'!G63/'Data Sheet'!G$75 -> 0.061375225 | I32: ='Data Sheet'!H63/'Data Sheet'!H$75 -> 0.031152506 | J32: ='Data Sheet'!I63/'Data Sheet'!I$75 -> 0.042651899 | ... L32: ='Data Sheet'!K63/'Data Sheet'!K$75 -> 0.17456423
B33: ='Data Sheet'!A64 -> Investments | C33: ='Data Sheet'!B64/'Data Sheet'!B$75 -> 0.090305676 | D33: ='Data Sheet'!C64/'Data Sheet'!C$75 -> 0.074612566 | E33: ='Data Sheet'!D64/'Data Sheet'!D$75 -> 0.063610241 | F33: ='Data Sheet'!E64/'Data Sheet'!E$75 -> 0.051588289 | G33: ='Data Sheet'!F64/'Data Sheet'!F$75 -> 0.050935446 | H33: ='Data Sheet'!G64/'Data Sheet'!G$75 -> 0.072079768 | I33: ='Data Sheet'!H64/'Data Sheet'!H$75 -> 0.089282796 | J33: ='Data Sheet'!I64/'Data Sheet'!I$75 -> 0.078820363 | ... L33: ='Data Sheet'!K64/'Data Sheet'!K$75 -> 0.094585023
B34: ='Data Sheet'!A65 -> Other Assets | C34: ='Data Sheet'!B65/'Data Sheet'!B$75 -> 0.40377208 | D34: ='Data Sheet'!C65/'Data Sheet'!C$75 -> 0.44977386 | E34: ='Data Sheet'!D65/'Data Sheet'!D$75 -> 0.44295638 | F34: ='Data Sheet'!E65/'Data Sheet'!E$75 -> 0.48025117 | G34: ='Data Sheet'!F65/'Data Sheet'!F$75 -> 0.44082 | H34: ='Data Sheet'!G65/'Data Sheet'!G$75 -> 0.46045651 | I34: ='Data Sheet'!H65/'Data Sheet'!H$75 -> 0.45759053 | J34: ='Data Sheet'!I65/'Data Sheet'!I$75 -> 0.48387626 | ... L34: ='Data Sheet'!K65/'Data Sheet'!K$75 -> 0.42394018
B35: ='Data Sheet'!A67 -> Receivables | C35: ='Data Sheet'!B67/'Data Sheet'!B$75 -> 0.051564319 | D35: ='Data Sheet'!C67/'Data Sheet'!C$75 -> 0.051638166 | E35: ='Data Sheet'!D67/'Data Sheet'!D$75 -> 0.060800116 | F35: ='Data Sheet'!E67/'Data Sheet'!E$75 -> 0.062139199 | G35: ='Data Sheet'!F67/'Data Sheet'!F$75 -> 0.034895094 | H35: ='Data Sheet'!G67/'Data Sheet'!G$75 -> 0.037120014 | I35: ='Data Sheet'!H67/'Data Sheet'!H$75 -> 0.037810927 | J35: ='Data Sheet'!I67/'Data Sheet'!I$75 -> 0.047024716 | ... L35: ='Data Sheet'!K67/'Data Sheet'!K$75 -> 0.0351431
B36: ='Data Sheet'!A68 -> Inventory | C36: ='Data Sheet'!B68/'Data Sheet'!B$75 -> 0.12407941 | D36: ='Data Sheet'!C68/'Data Sheet'!C$75 -> 0.12871547 | E36: ='Data Sheet'!D68/'Data Sheet'!D$75 -> 0.12878571 | F36: ='Data Sheet'!E68/'Data Sheet'!E$75 -> 0.12761951 | G36: ='Data Sheet'!F68/'Data Sheet'!F$75 -> 0.11698717 | H36: ='Data Sheet'!G68/'Data Sheet'!G$75 -> 0.10565506 | I36: ='Data Sheet'!H68/'Data Sheet'!H$75 -> 0.10709348 | J36: ='Data Sheet'!I68/'Data Sheet'!I$75 -> 0.12177623 | ... L36: ='Data Sheet'!K68/'Data Sheet'!K$75 -> 0.12539094
B37: ='Data Sheet'!A69 -> Cash & Bank | C37: ='Data Sheet'!B69/'Data Sheet'!B$75 -> 0.11573799 | D37: ='Data Sheet'!C69/'Data Sheet'!C$75 -> 0.13235686 | E37: ='Data Sheet'!D69/'Data Sheet'!D$75 -> 0.10579088 | F37: ='Data Sheet'!E69/'Data Sheet'!E$75 -> 0.10679898 | G37: ='Data Sheet'!F69/'Data Sheet'!F$75 -> 0.10533773 | H37: ='Data Sheet'!G69/'Data Sheet'!G$75 -> 0.13699234 | I37: ='Data Sheet'!H69/'Data Sheet'!H$75 -> 0.12359146 | J37: ='Data Sheet'!I69/'Data Sheet'!I$75 -> 0.1106017 | ... L37: ='Data Sheet'!K69/'Data Sheet'!K$75 -> 0.10832076
B39: Total Asset | C39: ='Data Sheet'!B75/'Data Sheet'!B$75 -> 1 | D39: ='Data Sheet'!C75/'Data Sheet'!C$75 -> 1 | E39: ='Data Sheet'!D75/'Data Sheet'!D$75 -> 1 | F39: ='Data Sheet'!E75/'Data Sheet'!E$75 -> 1 | G39: ='Data Sheet'!F75/'Data Sheet'!F$75 -> 1 | H39: ='Data Sheet'!G75/'Data Sheet'!G$75 -> 1 | I39: ='Data Sheet'!H75/'Data Sheet'!H$75 -> 1 | J39: ='Data Sheet'!I75/'Data Sheet'!I$75 -> 1 | ... L39: ='Data Sheet'!K75/'Data Sheet'!K$75 -> 1

Sheet Forcasting
B3: ='Data Sheet'!B1&" - "&'Data Sheet'!A17 -> TATA MOTORS LTD - Sales | G3: ='Data Sheet'!B1&" - "&HistoricaIFS!B17 -> TATA MOTORS LTD - EBITDA | L3: ='Data Sheet'!B1&" - "&HistoricaIFS!B37 -> TATA MOTORS LTD - EPS
B4: Year Weight | C4: Year | D4: Sales | E4: Sales Growth | G4: Year Weight | H4: Year | I4: EBITDA | J4: EBITDA Growth | L4: Year Weight | M4: Year | N4: EPS | O4: EPS Growth
B5: 1 | C5: 2016 | D5: {=TRANSPOSE('Data Sheet'!B17:K17)} -> 273045.6 | G5: 1 | H5: 2016 | I5: {=TRANSPOSE(HistoricaIFS!C17:L17)} -> 38395.25 | L5: 1 | M5: 2016 | N5: {=TRANSPOSE(HistoricaIFS!C37:L37)} -> 10.244216
B6: 2 | C6: 2017 | D6: 269692.51 | E6: =IFERROR(D6/D5-1,0) -> -0.01228033 | G6: 2 | H6: 2017 | I6: 29588.69 | J6: =IFERROR(I6/I5-1,0) -> -0.22936587 | L6: 2 | M6: 2017 | N6: 18.729574 | O6: =IFERROR(N6/N5-1,0) -> 0.82830727
B7: 3 | C7: 2018 | D7: 291550.48 | E7: =IFERROR(D7/D6-1,0) -> 0.081047746 | G7: 3 | H7: 2018 | I7: 31457.68 | J7: =IFERROR(I7/I6-1,0) -> 0.063165689 | L7: 3 | M7: 2018 | N7: 11.093409 | O7: =IFERROR(N7/N6-1,0) -> -0.40770629
B8: 4 | C8: 2019 | D8: 301938.4 | E8: =IFERROR(D8/D7-1,0) -> 0.035629919 | G8: 4 | H8: 2019 | I8: 24664.33 | J8: =IFERROR(I8/I7-1,0) -> -0.21595203 | L8: 4 | M8: 2019 | N8: 13.036401 | O8: =IFERROR(N8/N7-1,0) -> 0.1751483
B9: 5 | C9: 2020 | D9: 261067.97 | E9: =IFERROR(D9/D8-1,0) -> -0.13536016 | G9: 5 | H9: 2020 | I9: 17987.07 | J9: =IFERROR(I9/I8-1,0) -> -0.27072538 | L9: 5 | M9: 2020 | N9: 22.741988 | O9: =IFERROR(N9/N8-1,0) -> 0.74449897
B10: 6 | C10: 2021 | D10: 249794.75 | E10: =IFERROR(D10/D9-1,0) -> -0.043181168 | G10: 6 | H10: 2021 | I10: 32287.43 | J10: =IFERROR(I10/I9-1,0) -> 0.79503554 | L10: 6 | M10: 2021 | N10: 52.425986 | O10: =IFERROR(N10/N9-1,0) -> 1.3052508
B11: 7 | C11: 2022 | D11: 278453.62 | E11: =IFERROR(D11/D10-1,0) -> 0.11472967 | G11: 7 | H11: 2022 | I11: 24720.09 | J11: =IFERROR(I11/I10-1,0) -> -0.23437418 | L11: 7 | M11: 2022 | N11: 16.761526 | O11: =IFERROR(N11/N10-1,0) -> -0.6802821
B12: 8 | C12: 2023 | D12: 345966.97 | E12: =IFERROR(D12/D11-1,0) -> 0.24245815 | G12: 8 | H12: 2023 | I12: 31815.8 | J12: =IFERROR(I12/I11-1,0) -> 0.28704224 | L12: 8 | M12: 2023 | N12: 10.065336 | O12: =IFERROR(N12/N11-1,0) -> -0.39949765
B13: 9 | C13: 2024 | D13: 434016 | E13: =IFERROR(D13/D12-1,0) -> 0.25450126 | G13: 9 | H13: 2024 | I13: 57824 | J13: =IFERROR(I13/I12-1,0) -> 0.81746176 | L13: 9 | M13: 2024 | N13: 16.265006 | O13: =IFERROR(N13/N12-1,0) -> 0.61594269
B14: 10 | C14: 2025 | D14: 439695 | E14: =IFERROR(D14/D13-1,0) -> 0.013084771 | G14: 10 | H14: 2025 | I14: 55216 | J14: =IFERROR(I14/I13-1,0) -> -0.04510238 | L14: 10 | M14: 2025 | N14: 23.008176 | O14: =IFERROR(N14/N13-1,0) -> 0.4145815
B15: 11 | C15: 2026 | D15: =FORECAST(B15,D5:D14,B5:B14) -> 409204.26 | E15: =IFERROR(D15/D14-1,0) -> -0.069345204 | G15: 11 | H15: 2026 | I15: =FORECAST(G15,I5:I14,G5:G14) -> 46572.039 | J15: =IFERROR(I15/I14-1,0) -> -0.15654811 | L15: 11 | M15: 2026 | N15: =FORECAST(L15,N5:N14,L5:L14) -> 23.881918 | O15: =IFERROR(N15/N14-1,0) -> 0.037975244
B16: 12 | C16: 2027 | D16: =FORECAST(B16,D5:D15,B5:B15) -> 426419.19 | E16: =IFERROR(D16/D15-1,0) -> 0.04206929 | G16: 12 | H16: 2027 | I16: =FORECAST(G16,I6:I15,G6:G15) -> 52509.166 | J16: =IFERROR(I16/I15-1,0) -> 0.12748264 | L16: 12 | M16: 2027 | N16: =FORECAST(L16,N6:N15,L6:L15) -> 23.208368 | O16: =IFERROR(N16/N15-1,0) -> -0.028203343
B17: 13 | C17: 2028 | D17: =FORECAST(B17,D5:D16,B5:B16) -> 443634.13 | E17: =IFERROR(D17/D16-1,0) -> 0.040370915 | G17: 13 | H17: 2028 | I17: =FORECAST(G17,I7:I16,G7:G16) -> 57927.607 | J17: =IFERROR(I17/I16-1,0) -> 0.1031904 | L17: 13 | M17: 2028 | N17: =FORECAST(L17,N7:N16,L7:L16) -> 23.61898 | O17: =IFERROR(N17/N16-1,0) -> 0.017692423
B18: 14 | C18: 2029 | D18: =FORECAST(B18,D6:D17,B6:B17) -> 468483.44 | E18: =IFERROR(D18/D17-1,0) -> 0.056013087 | G18: 14 | H18: 2029 | I18: =FORECAST(G18,I8:I17,G8:G17) -> 64483.791 | J18: =IFERROR(I18/I17-1,0) -> 0.11317892 | L18: 14 | M18: 2029 | N18: =FORECAST(L18,N8:N17,L8:L17) -> 21.85894 | O18: =IFERROR(N18/N17-1,0) -> -0.074518028
B19: 15 | C19: 2030 | D19: =FORECAST(B19,D7:D18,B7:B18) -> 493150.58 | E19: =IFERROR(D19/D18-1,0) -> 0.052653167 | G19: 15 | H19: 2030 | I19: =FORECAST(G19,I9:I18,G9:G18) -> 70086.227 | J19: =IFERROR(I19/I18-1,0) -> 0.086881301 | L19: 15 | M19: 2030 | N19: =FORECAST(L19,N9:N18,L9:L18) -> 19.077977 | O19: =IFERROR(N19/N18-1,0) -> -0.12722312
B29: Arithmatic Mean | C29: =IFERROR(AVERAGE(E5:E14),0) -> 0.061181096 | Q29: Arithmatic Mean | R29: =IFERROR(AVERAGE(T5:T14),0) -> 0
B30: Geometric Mean | C30: =_xlfn.RRI(B14,D5,D14) -> 0.048797478 | Q30: Geometric Mean | R30: =_xlfn.RRI(Q14,S5,S14) -> #NUM!
B32: Standard Deviation | C32: =_xlfn.STDEV.S(E5:E14) -> 0.12814974 | Q32: Standard Deviation | R32: =_xlfn.STDEV.S(T5:T14) -> #DIV/0!

Sheet WACC
B2: Weighted Average Cost of Capital
B4: All Figures are in INR Unless satrted otherwise
B6: Peer Comps
J7: Debt / | K7: Debt/ | L7: Leverd | M7: Unleverd
B8: Name Of The Comp | F8: Country | G8: Total Debt | H8: Total Equity | I8: Tax Rate 1 | J8: Equity | K8: Capital | L8: Beta 2 | M8: Beta 3
O9: =G10 -> 819.62
B10: ='Beta - Comp '!C4 -> Avenue Super. | F10: India | G10: ='Beta - Comp '!F4 -> 819.62 | H10: ='Beta - Comp '!E4 -> 261737.44 | I10: 0.3 | J10: =G10/H10 -> 0.0031314588 | K10: =G10/(G10+H10) -> 0.0031216833 | L10: =Beta!N8 -> 1.2414891 | M10: =L10/(1+(1-I10)*J10) -> 1.2387737 | O10: =H10+G10 -> 262557.06
B11: ='Beta - Comp '!C5 -> Trent | F11: India | G11: ='Beta - Comp '!F5 -> 2237.19 | H11: ='Beta - Comp '!E5 -> 183059.4 | I11: 0.3 | J11: =G11/H11 -> 0.012221115 | K11: =G11/(G11+H11) -> 0.012073563 | L11: 1.54 | M11: =L11/(1+(1-I11)*J11) -> 1.5269374
B12: ='Beta - Comp '!C9 -> Vedant Fashions | F12: India | G12: ='Beta - Comp '!F9 -> 482.9 | H12: ='Beta - Comp '!E9 -> 19296.24 | I12: 0.3 | J12: =G12/H12 -> 0.025025601 | K12: =G12/(G12+H12) -> 0.024414611 | L12: 0.61 | M12: =L12/(1+(1-I12)*J12) -> 0.59949804 | O12: =O9/O10 -> 0.0031216833
B13: ='Beta - Comp '!C15 -> Aditya Bir. Fas. | F13: India | G13: ='Beta - Comp '!F15 -> 5016.78 | H13: ='Beta - Comp '!E15 -> 9234.98 | I13: 0.3 | J13: =G13/H13 -> 0.54323669 | K13: =G13/(G13+H13) -> 0.35201126 | L13: 0.93 | M13: =L13/(1+(1-I13)*J13) -> 0.67378332
B14: Metro Brands | F14: India | G14: ='Beta - Comp '!F17 -> 1227.08 | H14: ='Beta - Comp '!E17 -> 32844.94 | I14: 0.3 | J14: =G14/H14 -> 0.037359788 | K14: =G14/(G14+H14) -> 0.036014301 | L14: 0.79 | M14: =L14/(1+(1-I14)*J14) -> 0.76986656
H17: Average | I17: =AVERAGE(I10:I14) -> 0.3 | J17: =AVERAGE(J10:J14) -> 0.12419493 | K17: =AVERAGE(K10:K14) -> 0.085527084 | L17: =AVERAGE(L10:L14) -> 1.0222978 | M17: =AVERAGE(M10:M14) -> 0.9617718
H18: Median | I18: =MEDIAN(I10:I14) -> 0.3 | J18: =MEDIAN(J10:J14) -> 0.025025601 | K18: =MEDIAN(K10:K14) -> 0.024414611 | L18: =MEDIAN(L10:L14) -> 0.93 | M18: =MEDIAN(M10:M14) -> 0.76986656
B21: Cost Of Debt | H21: Cost Of Equity
B23: Pre -Tax Cost Of Debt | E23: 0.084 | H23: Risk Free rate | M23: 0.0739
B24: Tax Rate | E24: 0.3 | H24: Equity Risk Primium | M24: ='Rm '!G8-WACC!M23 -> 0.079448
B25: Post -Tax Cost Of Debt | E25: =E23*(1-E24) -> 0.0588 | H25: Levered Beta 4 | M25: =M34 -> 0.82026839
H26: Cost Of Equity | M26: =M23+M24*M25 -> 0.13906868
B29: Capital Structure | H29: Leveard Beta
D31: Current | E31: Target | H31: Comps Median Unleverad Beta | M31: =M18 -> 0.76986656
B32: Total Debt | C32: =G10 -> 819.62 | D32: =C32/$C$34 -> 0.0031216833 | E32: =K17 -> 0.085527084 | H32: Target Rate /Equity | M32: =E36 -> 0.093526098
B33: Market Capitalization | C33: =H10 -> 261737.44 | D33: =C33/$C$34 -> 0.99687832 | E33: =E34-E32 -> 0.91447292 | H33: =B24 -> Tax Rate | M33: =E24 -> 0.3
B34: Total Capital | C34: =C32+C33 -> 262557.06 | D34: =D32+D33 -> 1 | E34: 1 | H34: Leverad Beta | M34: =M31*(1+(1-M33)*M32) -> 0.82026839
B36: Debt / Equity | D36: =D32/D33 -> 0.0031314588 | E36: =E32/E33 -> 0.093526098
H37: =B2 -> Weighted Average Cost of Capital
B38: 1. Tax Rate considered as Marginal Tax Rate for the country
B39: 2. Levered Beta is based on 2 year Weekly data | H39: Cost Of Debt | M39: =E25 -> 0.0588
B40: 3. Unlevered Beta = Levered Beta/(1+(1-Tax Rate) x Debt/Equity) | H40: Debt Weight | M40: =E32 -> 0.085527084
B41: 3. Levered Beta = Unlevered Beta/(1+(1-Tax Rate) x Debt/Equity)
H42: Cost of Equity | M42: =M26 -> 0.13906868
H43: Equity Weight | M43: =E33 -> 0.91447292
H45: WACC | M45: =(M39*M40)+(M42*M43) -> 0.13220354

Sheet Beta
B2: Avenue Supermart Weekly Report | F2: NIFTY Returns | I2: Beta drifting
B4: Date | C4: Closing Price | D4: Return | F4: Closing Price | G4: Return
B5: 44249 | C5: 2994.2 | F5: 14529.2 | I5: Leaverged Raw Beta | J5: =N5 -> 1.2414891 | M5: Beta 1 | N5: =SLOPE(D5:D109,G5:G109) -> 1.2414891
B6: 44256 | C6: 3286.1 | D6: 0.0975 | F6: 14938.1 | G6: 0.0281 | I6: Raw Beta Weight | J6: 0.75 | M6: beta2 | N6: =_xlfn.COVARIANCE.S(D5:D109,G5:G109)/_xlfn.VAR.S(G5:G109) -> 1.2414891
B7: 44263 | C7: 3129.4 | D7: -0.0477 | F7: 15031 | G7: 0.0062
B8: 44270 | C8: 2960.3 | D8: -0.054 | F8: 14744 | G8: -0.0191 | I8: Market Raw Beta | J8: 1 | M8: Beta 3 | N8: =N27 -> 1.2414891
B9: 44277 | C9: 2855.2 | D9: -0.0355 | F9: 14507.3 | G9: -0.0161 | I9: Market Beta Weight | J9: 0.25
B10: 44284 | C10: 2912.7 | D10: 0.0201 | F10: 14867.3 | G10: 0.0248 | M10: SUMMARY OUTPUT
B11: 44291 | C11: 2947.8 | D11: 0.012 | F11: 14834.8 | G11: -0.0022
B12: 44298 | C12: 2919.9 | D12: -0.0094 | F12: 14617.8 | G12: -0.0146 | I12: Adjusted Beta | J12: =(J5*J6)+(J8*J9) -> 1.1811168 | M12: Regression Statistics
B13: 44305 | C13: 2713.7 | D13: -0.0706 | F13: 14341.3 | G13: -0.0189 | M13: Multiple R | N13: 0.51083871
B14: 44312 | C14: 2852.9 | D14: 0.0513 | F14: 14631.1 | G14: 0.0202 | M14: R Square | N14: 0.26095619
B15: 44319 | C15: 2895.5 | D15: 0.0149 | F15: 14823.2 | G15: 0.0131 | M15: Adjusted R Square | N15: 0.25371066
B16: 44326 | C16: 2844.6 | D16: -0.0176 | F16: 14677.8 | G16: -0.0098 | M16: Standard Error | N16: 0.042295755
B17: 44333 | C17: 3034.1 | D17: 0.0666 | F17: 15175.3 | G17: 0.0339 | M17: Observations | N17: 104
B18: 44340 | C18: 3022.1 | D18: -0.004 | F18: 15435.7 | G18: 0.0172
B19: 44347 | C19: 3197 | D19: 0.0579 | F19: 15670.3 | G19: 0.0152 | M19: ANOVA
B20: 44354 | C20: 3175.6 | D20: -0.0067 | F20: 15799.3 | G20: 0.0082 | N20: df | O20: SS | P20: MS | Q20: F | R20: Significance F
B21: 44361 | C21: 3317.7 | D21: 0.0448 | F21: 15683.3 | G21: -0.0073 | M21: Regression | N21: 1 | O21: 0.064430448 | P21: 0.064430448 | Q21: 36.016175 | R21: 3.0154038e-08
B22: 44368 | C22: 3315.4 | D22: -0.0007 | F22: 15860.3 | G22: 0.0113 | M22: Residual | N22: 102 | O22: 0.18247095 | P22: 0.0017889309
B23: 44375 | C23: 3314.3 | D23: -0.0003 | F23: 15722.2 | G23: -0.0087 | M23: Total | N23: 103 | O23: 0.2469014
B24: 44382 | C24: 3377.6 | D24: 0.0191 | F24: 15689.8 | G24: -0.0021
B25: 44389 | C25: 3349.2 | D25: -0.0084 | F25: 15923.4 | G25: 0.0149 | N25: Coefficients | O25: Standard Error | P25: t Stat | Q25: P-value | R25: Lower 95% | S25: Upper 95% | T25: Lower 95.0% | U25: Upper 95.0%
B26: 44396 | C26: 3413.2 | D26: 0.0191 | F26: 15856 | G26: -0.0042 | M26: Intercept | N26: 0.00011322271 | O26: 0.0041717746 | P26: 0.027140179 | Q26: 0.97840096 | R26: -0.0081614725 | S26: 0.0083879179 | T26: -0.0081614725 | U26: 0.0083879179
B27: 44403 | C27: 3500.8 | D27: 0.0257 | F27: 15763 | G27: -0.0059 | M27: X Variable 1 | N27: 1.2414891 | O27: 0.20686838 | P27: 6.0013477 | Q27: 3.0154038e-08 | R27: 0.83116666 | S27: 1.6518116 | T27: 0.83116666 | U27: 1.6518116
B28: 44410 | C28: 3529.2 | D28: 0.0081 | F28: 16238.2 | G28: 0.0301
B29: 44417 | C29: 3594.6 | D29: 0.0185 | F29: 16529.1 | G29: 0.0179
B30: 44424 | C30: 3643.1 | D30: 0.0135 | F30: 16450.5 | G30: -0.0048
B31: 44431 | C31: 3833.1 | D31: 0.0521 | F31: 16705.2 | G31: 0.0155
B32: 44438 | C32: 3938.9 | D32: 0.0276 | F32: 17323.6 | G32: 0.037
B33: 44445 | C33: 3950.5 | D33: 0.0029 | F33: 17369.3 | G33: 0.0026
B34: 44452 | C34: 4239.6 | D34: 0.0732 | F34: 17585.2 | G34: 0.0124
B35: 44459 | C35: 4422.4 | D35: 0.0431 | F35: 17853.2 | G35: 0.0152
B36: 44466 | C36: 4235.6 | D36: -0.0422 | F36: 17532.1 | G36: -0.018
B37: 44473 | C37: 4408 | D37: 0.0407 | F37: 17895.2 | G37: 0.0207
B38: 44480 | C38: 5323.8 | D38: 0.2078 | F38: 18338.6 | G38: 0.0248
B39: 44487 | C39: 4521.5 | D39: -0.1507 | F39: 18114.9 | G39: -0.0122
... B109: 44977 | C109: 3552.9 | D109: 0.0022 | F109: 17844.6 | G109: -0.0056

Sheet Beta  - Comp 
B3: S.No. | C3: Name | D3: CMP Rs. | E3: Mar Cap Rs.Cr. | F3: Debt Rs.Cr. | G3: Debt / Eq
B4: 2 | C4: Avenue Super. | D4: 4021 | E4: 261737.44 | F4: 819.62 | G4: 0.04
B5: 3 | C5: Trent | D5: 5154 | E5: 183059.4 | F5: 2237.19 | G5: 0.41
B6: 5 | C6: Info Edg.(India) | D6: 1457.2 | E6: 94431 | F6: 267.34 | G6: 0.01
B7: 6 | C7: Vishal Mega Mart | D7: 140.01 | E7: 65277.75 | F7: 1729.38 | G7: 0.27
B8: 7 | C8: FSN E-Commerce | D8: 215.62 | E8: 61731.33 | F8: 1320.59 | G8: 1.01
B9: 8 | C9: Vedant Fashions | D9: 794.3 | E9: 19296.24 | F9: 482.9 | G9: 0.27
B10: 9 | C10: Brainbees Solut. | D10: 358.25 | E10: 18650.67 | F10: 1569.93 | G10: 0.33
B11: 10 | C11: A B Lifestyle | D11: 149.77 | E11: 18270.33 | F11: 2932.45 | G11: 2.3
B12: 11 | C12: Indiamart Inter. | D12: 2621 | E12: 15794.78 | F12: 33.04 | G12: 0.02
B13: 12 | C13: Medplus Health | D13: 887.2 | E13: 10615.24 | F13: 1119.8 | G13: 0.64
B14: 13 | C14: Cartrade Tech | D14: 1965.6 | E14: 9322.13 | F14: 131.37 | G14: 0.06
B15: 14 | C15: Aditya Bir. Fas. | D15: 75.67 | E15: 9234.98 | F15: 5016.78 | G15: 0.74
... B17: 16 | C17: Metro Brands | D17: 1205.7 | E17: 32844.94 | F17: 1227.08 | G17: 0.72

Sheet DATA>

Sheet Ratio Analysis
B2: ="Ratio Analysis - "&'Data Sheet'!B1 -> Ratio Analysis - TATA MOTORS LTD
B3: Years | C3: ='Data Sheet'!B16 -> 42460 | D3: ='Data Sheet'!C16 -> 42825 | E3: ='Data Sheet'!D16 -> 43190 | F3: ='Data Sheet'!E16 -> 43555 | G3: ='Data Sheet'!F16 -> 43921 | H3: ='Data Sheet'!G16 -> 44286 | I3: ='Data Sheet'!H16 -> 44651 | J3: ='Data Sheet'!I16 -> 45016 | ... L3: ='Data Sheet'!K16 -> 45747 | M3: Trend | N3: Mean | O3: Median
B5: Sales Growth | D5: =HistoricaIFS!D6 -> -0.01228033 | E5: =HistoricaIFS!E6 -> 0.081047746 | F5: =HistoricaIFS!F6 -> 0.035629919 | G5: =HistoricaIFS!G6 -> -0.13536016 | H5: =HistoricaIFS!H6 -> -0.043181168 | I5: =HistoricaIFS!I6 -> 0.11472967 | J5: =HistoricaIFS!J6 -> 0.24245815 | K5: =HistoricaIFS!K6 -> 0.25450126 | L5: =HistoricaIFS!L6 -> 0.013084771 | N5: =IFERROR(AVERAGE(D5:L5),0) -> 0.061181096 | O5: =IFERROR(MEDIAN(D5:L5),0) -> 0.035629919
B6: EBITDA Growth | D6: =HistoricaIFS!D17/HistoricaIFS!C17-1 -> -0.22936587 | E6: =HistoricaIFS!E17/HistoricaIFS!D17-1 -> 0.063165689 | F6: =HistoricaIFS!F17/HistoricaIFS!E17-1 -> -0.21595203 | G6: =HistoricaIFS!G17/HistoricaIFS!F17-1 -> -0.27072538 | H6: =HistoricaIFS!H17/HistoricaIFS!G17-1 -> 0.79503554 | I6: =HistoricaIFS!I17/HistoricaIFS!H17-1 -> -0.23437418 | J6: =HistoricaIFS!J17/HistoricaIFS!I17-1 -> 0.28704224 | K6: =HistoricaIFS!K17/HistoricaIFS!J17-1 -> 0.81746176 | L6: =HistoricaIFS!L17/HistoricaIFS!K17-1 -> -0.04510238 | N6: =IFERROR(AVERAGE(D6:L6),0) -> 0.10746504 | O6: =IFERROR(MEDIAN(D6:L6),0) -> -0.04510238
B7: EBIT Growth | D7: =IFERROR(HistoricaIFS!D26-HistoricaIFS!C26-1,0) -> -9350.7 | E7: =IFERROR(HistoricaIFS!E26-HistoricaIFS!D26-1,0) -> -2224.39 | F7: =IFERROR(HistoricaIFS!F26-HistoricaIFS!E26-1,0) -> -9908.2 | G7: =IFERROR(HistoricaIFS!G26-HistoricaIFS!F26-1,0) -> -5997.79 | H7: =IFERROR(HistoricaIFS!H26-HistoricaIFS!G26-1,0) -> 11324.24 | I7: =IFERROR(HistoricaIFS!I26-HistoricaIFS!H26-1,0) -> -10072.01 | J7: =IFERROR(HistoricaIFS!J26-HistoricaIFS!I26-1,0) -> 6156.42 | K7: =IFERROR(HistoricaIFS!K26-HistoricaIFS!J26-1,0) -> 26260.04 | L7: =IFERROR(HistoricaIFS!L26-HistoricaIFS!K26-1,0) -> 3885 | N7: =IFERROR(AVERAGE(D7:L7),0) -> 1119.1789 | O7: =IFERROR(MEDIAN(D7:L7),0) -> -2224.39
B8: Net Profit Growth | D8: =IFERROR((HistoricaIFS!D32/HistoricaIFS!C32-1),0) -> 0.8283706 | E8: =IFERROR((HistoricaIFS!E32/HistoricaIFS!D32-1),0) -> -0.40770629 | F8: =IFERROR((HistoricaIFS!F32/HistoricaIFS!E32-1),0) -> 0.1751483 | G8: =IFERROR((HistoricaIFS!G32/HistoricaIFS!F32-1),0) -> 0.86636557 | H8: =IFERROR((HistoricaIFS!H32/HistoricaIFS!G32-1),0) -> 1.4778648 | I8: =IFERROR((HistoricaIFS!I32/HistoricaIFS!H32-1),0) -> -0.68024358 | J8: =IFERROR((HistoricaIFS!J32/HistoricaIFS!I32-1),0) -> -0.39938915 | K8: =IFERROR((HistoricaIFS!K32/HistoricaIFS!J32-1),0) -> 0.61711038 | L8: =IFERROR((HistoricaIFS!L32/HistoricaIFS!K32-1),0) -> 0.56677765 | N8: =IFERROR(AVERAGE(D8:L8),0) -> 0.33825536 | O8: =IFERROR(MEDIAN(D8:L8),0) -> 0.56677765
B9: Dividend Growth | D9: =IFERROR(HistoricaIFS!D40/HistoricaIFS!C40-1,0) -> -1 | E9: =IFERROR(HistoricaIFS!E40/HistoricaIFS!D40-1,0) -> 0 | F9: =IFERROR(HistoricaIFS!F40/HistoricaIFS!E40-1,0) -> 0 | G9: =IFERROR(HistoricaIFS!G40/HistoricaIFS!F40-1,0) -> 0 | H9: =IFERROR(HistoricaIFS!H40/HistoricaIFS!G40-1,0) -> 0 | I9: =IFERROR(HistoricaIFS!I40/HistoricaIFS!H40-1,0) -> 0 | J9: =IFERROR(HistoricaIFS!J40/HistoricaIFS!I40-1,0) -> 0 | K9: =IFERROR(HistoricaIFS!K40/HistoricaIFS!J40-1,0) -> 2.001669 | L9: =IFERROR(HistoricaIFS!L40/HistoricaIFS!K40-1,0) -> -0.1336307 | N9: =IFERROR(AVERAGE(D9:L9),0) -> 0.096448699 | O9: =IFERROR(MEDIAN(D9:L9),0) -> 0
B11: Gross Margine | C11: =IFERROR(HistoricaIFS!C9,0) -> 0.75265476 | D11: =IFERROR(HistoricaIFS!D9,0) -> 0.76180922 | E11: =IFERROR(HistoricaIFS!E9,0) -> 0.7835001 | F11: =IFERROR(HistoricaIFS!F9,0) -> 0.80428833 | G11: =IFERROR(HistoricaIFS!G9,0) -> 0.80582873 | H11: =IFERROR(HistoricaIFS!H9,0) -> 0.78194614 | I11: =IFERROR(HistoricaIFS!I9,0) -> 0.80192892 | J11: =IFERROR(HistoricaIFS!J9,0) -> 0.79314982 | ... L11: =IFERROR(HistoricaIFS!L9,0) -> 0.7751032 | N11: =IFERROR(AVERAGE(D11:L11),0) -> 0.78644299 | O11: =IFERROR(MEDIAN(D11:L11),0) -> 0.7835001
B12: EBITDA Magrine | C12: =IFERROR(HistoricaIFS!C18,0) -> 0.14061845 | D12: =IFERROR(HistoricaIFS!D18,0) -> 0.10971269 | E12: =IFERROR(HistoricaIFS!E18,0) -> 0.10789788 | F12: =IFERROR(HistoricaIFS!F18,0) -> 0.081686629 | G12: =IFERROR(HistoricaIFS!G18,0) -> 0.068898034 | H12: =IFERROR(HistoricaIFS!H18,0) -> 0.12925584 | I12: =IFERROR(HistoricaIFS!I18,0) -> 0.088776328 | J12: =IFERROR(HistoricaIFS!J18,0) -> 0.091961958 | ... L12: =IFERROR(HistoricaIFS!L18,0) -> 0.12557796 | N12: =IFERROR(AVERAGE(D12:L12),0) -> 0.10411083 | O12: =IFERROR(MEDIAN(D12:L12),0) -> 0.10789788
B13: EBIT Margine | C13: =IFERROR(HistoricaIFS!C27,0) -> 0.061511301 | D13: =IFERROR(HistoricaIFS!D27,0) -> 0.027608071 | E13: =IFERROR(HistoricaIFS!E27,0) -> 0.017912164 | F13: =IFERROR(HistoricaIFS!F27,0) -> -0.015516079 | G13: =IFERROR(HistoricaIFS!G27,0) -> -0.04091536 | H13: =IFERROR(HistoricaIFS!H27,0) -> 0.0025763152 | I13: =IFERROR(HistoricaIFS!I27,0) -> -0.033856482 | J13: =IFERROR(HistoricaIFS!J27,0) -> -0.009451885 | ... L13: =IFERROR(HistoricaIFS!L27,0) -> 0.061126463 | N13: =IFERROR(AVERAGE(D13:L13),0) -> 0.0069395454 | O13: =IFERROR(MEDIAN(D13:L13),0) -> 0.0025763152
B14: EBIT Margine | C14: =(HistoricaIFS!C17-HistoricaIFS!C23)/HistoricaIFS!C5 -> 0.079417028 | D14: =(HistoricaIFS!D17-HistoricaIFS!D23)/HistoricaIFS!D5 -> 0.043322301 | E14: =(HistoricaIFS!E17-HistoricaIFS!E23)/HistoricaIFS!E5 -> 0.033970412 | F14: =(HistoricaIFS!F17-HistoricaIFS!F23)/HistoricaIFS!F5 -> 0.0035560233 | G14: =(HistoricaIFS!G17-HistoricaIFS!G23)/HistoricaIFS!G5 -> -0.013170363 | H14: =(HistoricaIFS!H17-HistoricaIFS!H23)/HistoricaIFS!H5 -> 0.034991608 | I14: =(HistoricaIFS!I17-HistoricaIFS!I23)/HistoricaIFS!I5 -> -0.00041514993 | J14: =(HistoricaIFS!J17-HistoricaIFS!J23)/HistoricaIFS!J5 -> 0.020104347 | ... L14: =(HistoricaIFS!L17-HistoricaIFS!L23)/HistoricaIFS!L5 -> 0.072686749 | N14: =IFERROR(AVERAGE(D14:L14),0) -> 0.029501742 | O14: =IFERROR(MEDIAN(D14:L14),0) -> 0.033970412
B15: Net Profit Margine | C15: =IFERROR(HistoricaIFS!C33,0) -> 0.010832293 | D15: =IFERROR(HistoricaIFS!D33,0) -> 0.020051688 | E15: =IFERROR(HistoricaIFS!E33,0) -> 0.010986091 | F15: =IFERROR(HistoricaIFS!F33,0) -> 0.012466119 | G15: =IFERROR(HistoricaIFS!G33,0) -> 0.026908701 | H15: =IFERROR(HistoricaIFS!H33,0) -> 0.069685212 | I15: =IFERROR(HistoricaIFS!I33,0) -> 0.019988966 | J15: =IFERROR(HistoricaIFS!J33,0) -> 0.0096627721 | ... L15: =IFERROR(HistoricaIFS!L33,0) -> 0.019263353 | N15: =IFERROR(AVERAGE(D15:L15),0) -> 0.022385407 | O15: =IFERROR(MEDIAN(D15:L15),0) -> 0.019263353
B17: SalesEXpenses %sales | C17: =IFERROR(HistoricaIFS!C15,0) -> 0.10672679 | D17: =IFERROR(HistoricaIFS!D15,0) -> 0.1284781 | E17: =IFERROR(HistoricaIFS!E15,0) -> 0.10860202 | F17: =IFERROR(HistoricaIFS!F15,0) -> 0.11402505 | G17: =IFERROR(HistoricaIFS!G15,0) -> 0.12527324 | H17: =IFERROR(HistoricaIFS!H15,0) -> 0.088798023 | I17: =IFERROR(HistoricaIFS!I15,0) -> 0.10929475 | J17: =IFERROR(HistoricaIFS!J15,0) -> 0.11488822 | ... L17: =IFERROR(HistoricaIFS!L15,0) -> 0.099318846 | N17: =IFERROR(AVERAGE(D17:L17),0) -> 0.10944619 | O17: =IFERROR(MEDIAN(D17:L17),0) -> 0.10929475
B18: Deprisiation%Sales | C18: =IFERROR(HistoricaIFS!C24,0) -> 0.061201426 | D18: =IFERROR(HistoricaIFS!D24,0) -> 0.066390387 | E18: =IFERROR(HistoricaIFS!E24,0) -> 0.073927472 | F18: =IFERROR(HistoricaIFS!F24,0) -> 0.078130605 | G18: =IFERROR(HistoricaIFS!G24,0) -> 0.082068398 | H18: =IFERROR(HistoricaIFS!H24,0) -> 0.094264231 | I18: =IFERROR(HistoricaIFS!I24,0) -> 0.089191478 | J18: =IFERROR(HistoricaIFS!J24,0) -> 0.071857611 | ... L18: =IFERROR(HistoricaIFS!L24,0) -> 0.052891209 | N18: =IFERROR(AVERAGE(D18:L18),0) -> 0.074609083 | O18: =IFERROR(MEDIAN(D18:L18),0) -> 0.073927472
B19: OperatinMargine%Sales | C19: =C13 -> 0.061511301 | D19: =D13 -> 0.027608071 | E19: =E13 -> 0.017912164 | F19: =F13 -> -0.015516079 | G19: =G13 -> -0.04091536 | H19: =H13 -> 0.0025763152 | I19: =I13 -> -0.033856482 | J19: =J13 -> -0.009451885 | ... L19: =L13 -> 0.061126463 | N19: =IFERROR(AVERAGE(D19:L19),0) -> 0.0069395454 | O19: =IFERROR(MEDIAN(D19:L19),0) -> 0.0025763152
B21: Return on Capital Employed | C21: =IFERROR((HistoricaIFS!C17-HistoricaIFS!C23)/SUM(HistoricaIFS!C47:C49),0) -> 0.1462081 | D21: =IFERROR((HistoricaIFS!D17-HistoricaIFS!D23)/SUM(HistoricaIFS!D47:D49),0) -> 0.085490986 | E21: =IFERROR((HistoricaIFS!E17-HistoricaIFS!E23)/SUM(HistoricaIFS!E47:E49),0) -> 0.053716114 | F21: =IFERROR((HistoricaIFS!F17-HistoricaIFS!F23)/SUM(HistoricaIFS!F47:F49),0) -> 0.0064542734 | G21: =IFERROR((HistoricaIFS!G17-HistoricaIFS!G23)/SUM(HistoricaIFS!G47:G49),0) -> -0.018302178 | H21: =IFERROR((HistoricaIFS!H17-HistoricaIFS!H23)/SUM(HistoricaIFS!H47:H49),0) -> 0.044284325 | I21: =IFERROR((HistoricaIFS!I17-HistoricaIFS!I23)/SUM(HistoricaIFS!I47:I49),0) -> -0.00060520306 | J21: =IFERROR((HistoricaIFS!J17-HistoricaIFS!J23)/SUM(HistoricaIFS!J47:J49),0) -> 0.038762956 | ... L21: =IFERROR((HistoricaIFS!L17-HistoricaIFS!L23)/SUM(HistoricaIFS!L47:L49),0) -> 0.17028623 | N21: =IFERROR(AVERAGE(D21:L21),0) -> 0.059914835 | O21: =IFERROR(MEDIAN(D21:L21),0) -> 0.044284325
B22: Retained Earning | C22: =HistoricaIFS!C43 -> 0.76475478 | D22: =HistoricaIFS!D43 -> 1 | E22: =HistoricaIFS!E43 -> 1 | F22: =HistoricaIFS!F43 -> 1 | G22: =HistoricaIFS!G43 -> 1 | H22: =HistoricaIFS!H43 -> 1 | I22: =HistoricaIFS!I43 -> 1 | J22: =HistoricaIFS!J43 -> -1.3063861 | ... L22: =HistoricaIFS!L43 -> -4.9978812 | N22: =IFERROR(AVERAGE(D22:L22),0) -> -0.69191941 | O22: =IFERROR(MEDIAN(D22:L22),0) -> 1
B23: Return On Equity% | C23: =HistoricaIFS!C32/SUM(HistoricaIFS!C47:C48) -> 0.037461934 | D23: =HistoricaIFS!D32/SUM(HistoricaIFS!D47:D48) -> 0.093138374 | E23: =HistoricaIFS!E32/SUM(HistoricaIFS!E47:E48) -> 0.033564604 | F23: =HistoricaIFS!F32/SUM(HistoricaIFS!F47:F48) -> 0.062546154 | G23: =HistoricaIFS!G32/SUM(HistoricaIFS!G47:G48) -> 0.11136911 | H23: =HistoricaIFS!H32/SUM(HistoricaIFS!H47:H48) -> 0.31507753 | I23: =HistoricaIFS!I32/SUM(HistoricaIFS!I47:I48) -> 0.12490676 | J23: =HistoricaIFS!J32/SUM(HistoricaIFS!J47:J48) -> 0.073761429 | ... L23: =HistoricaIFS!L32/SUM(HistoricaIFS!L47:L48) -> 0.072926712 | N23: =IFERROR(AVERAGE(D23:L23),0) -> 0.10566134 | O23: =IFERROR(MEDIAN(D23:L23),0) -> 0.073761429
B24: Self sustained Growth Rate | C24: =IFERROR(C22*C23,0) -> 0.028649193 | D24: =IFERROR(D22*D23,0) -> 0.093138374 | E24: =IFERROR(E22*E23,0) -> 0.033564604 | F24: =IFERROR(F22*F23,0) -> 0.062546154 | G24: =IFERROR(G22*G23,0) -> 0.11136911 | H24: =IFERROR(H22*H23,0) -> 0.31507753 | I24: =IFERROR(I22*I23,0) -> 0.12490676 | J24: =IFERROR(J22*J23,0) -> -0.096360902 | ... L24: =IFERROR(L22*L23,0) -> -0.36447904 | N24: =IFERROR(AVERAGE(D24:L24),0) -> -0.010811605 | O24: =IFERROR(MEDIAN(D24:L24),0) -> 0.062546154
B25: Intrest Coverage Ratio | C25: =IFERROR((HistoricaIFS!C17-HistoricaIFS!C23)/HistoricaIFS!C20,0) -> 4.4352864 | D25: =IFERROR((HistoricaIFS!D17-HistoricaIFS!D23)/HistoricaIFS!D20,0) -> 2.7568835 | E25: =IFERROR((HistoricaIFS!E17-HistoricaIFS!E23)/HistoricaIFS!E20,0) -> 2.1154494 | F25: =IFERROR((HistoricaIFS!F17-HistoricaIFS!F23)/HistoricaIFS!F20,0) -> 0.18645157 | G25: =IFERROR((HistoricaIFS!G17-HistoricaIFS!G23)/HistoricaIFS!G20,0) -> -0.47469327 | H25: =IFERROR((HistoricaIFS!H17-HistoricaIFS!H23)/HistoricaIFS!H20,0) -> 1.0794784 | I25: =IFERROR((HistoricaIFS!I17-HistoricaIFS!I23)/HistoricaIFS!I20,0) -> -0.012414276 | J25: =IFERROR((HistoricaIFS!J17-HistoricaIFS!J23)/HistoricaIFS!J20,0) -> 0.6802067 | ... L25: =IFERROR((HistoricaIFS!L17-HistoricaIFS!L23)/HistoricaIFS!L20,0) -> 6.2876254 | N25: =IFERROR(AVERAGE(D25:L25),0) -> 1.8496121 | O25: =IFERROR(MEDIAN(D25:L25),0) -> 1.0794784
B27: Debtor Turnover Ratio | C27: =IFERROR(HistoricaIFS!C5/HistoricaIFS!C61,0) -> 20.119918 | D27: =IFERROR(HistoricaIFS!D5/HistoricaIFS!D61,0) -> 19.160353 | E27: =IFERROR(HistoricaIFS!E5/HistoricaIFS!E61,0) -> 14.655712 | F27: =IFERROR(HistoricaIFS!F5/HistoricaIFS!F61,0) -> 15.894699 | G27: =IFERROR(HistoricaIFS!G5/HistoricaIFS!G61,0) -> 23.366617 | H27: =IFERROR(HistoricaIFS!H5/HistoricaIFS!H61,0) -> 19.701331 | I27: =IFERROR(HistoricaIFS!I5/HistoricaIFS!I61,0) -> 22.379918 | J27: =IFERROR(HistoricaIFS!J5/HistoricaIFS!J61,0) -> 21.982948 | ... L27: =IFERROR(HistoricaIFS!L5/HistoricaIFS!L61,0) -> 33.189538 | N27: =IFERROR(AVERAGE(D27:L27),0) -> 21.770418 | O27: =IFERROR(MEDIAN(D27:L27),0) -> 21.982948
B28: Creditor Turnover Ratio | C28: =IFERROR(HistoricaIFS!C5/HistoricaIFS!C50,0) -> 2.3769604 | D28: =IFERROR(HistoricaIFS!D5/HistoricaIFS!D50,0) -> 1.9842808 | E28: =IFERROR(HistoricaIFS!E5/HistoricaIFS!E50,0) -> 2.041478 | F28: =IFERROR(HistoricaIFS!F5/HistoricaIFS!F50,0) -> 2.1667848 | G28: =IFERROR(HistoricaIFS!G5/HistoricaIFS!G50,0) -> 1.9731057 | H28: =IFERROR(HistoricaIFS!H5/HistoricaIFS!H50,0) -> 1.7323685 | I28: =IFERROR(HistoricaIFS!I5/HistoricaIFS!I50,0) -> 2.0170312 | J28: =IFERROR(HistoricaIFS!J5/HistoricaIFS!J50,0) -> 2.2286057 | ... L28: =IFERROR(HistoricaIFS!L5/HistoricaIFS!L50,0) -> 2.3228767 | N28: =IFERROR(AVERAGE(D28:L28),0) -> 2.1015458 | O28: =IFERROR(MEDIAN(D28:L28),0) -> 2.041478
B29: Inventry Turnover Ratio | C29: =IFERROR(HistoricaIFS!C5/HistoricaIFS!C62,0) -> 8.3613381 | D29: =IFERROR(HistoricaIFS!D5/HistoricaIFS!D62,0) -> 7.6867643 | E29: =IFERROR(HistoricaIFS!E5/HistoricaIFS!E62,0) -> 6.9190052 | F29: =IFERROR(HistoricaIFS!F5/HistoricaIFS!F62,0) -> 7.7392856 | G29: =IFERROR(HistoricaIFS!G5/HistoricaIFS!G62,0) -> 6.9698269 | H29: =IFERROR(HistoricaIFS!H5/HistoricaIFS!H62,0) -> 6.9217099 | I29: =IFERROR(HistoricaIFS!I5/HistoricaIFS!I62,0) -> 7.9015588 | J29: =IFERROR(HistoricaIFS!J5/HistoricaIFS!J62,0) -> 8.4888642 | ... L29: =IFERROR(HistoricaIFS!L5/HistoricaIFS!L62,0) -> 9.3019738 | N29: =IFERROR(AVERAGE(D29:L29),0) -> 7.8901224 | O29: =IFERROR(MEDIAN(D29:L29),0) -> 7.7392856
B30: Fixed Asset Turnover | C30: =IFERROR(HistoricaIFS!C5/HistoricaIFS!C54,0) -> 2.5463128 | D30: =IFERROR(HistoricaIFS!D5/HistoricaIFS!D54,0) -> 2.8109343 | E30: =IFERROR(HistoricaIFS!E5/HistoricaIFS!E54,0) -> 2.4012949 | F30: =IFERROR(HistoricaIFS!F5/HistoricaIFS!F54,0) -> 2.714432 | G30: =IFERROR(HistoricaIFS!G5/HistoricaIFS!G54,0) -> 2.0539206 | H30: =IFERROR(HistoricaIFS!H5/HistoricaIFS!H54,0) -> 1.8008727 | I30: =IFERROR(HistoricaIFS!I5/HistoricaIFS!I54,0) -> 2.0053489 | J30: =IFERROR(HistoricaIFS!J5/HistoricaIFS!J54,0) -> 2.6193792 | ... L30: =IFERROR(HistoricaIFS!L5/HistoricaIFS!L54,0) -> 3.800401 | N30: =IFERROR(AVERAGE(D30:L30),0) -> 2.6427849 | O30: =IFERROR(MEDIAN(D30:L30),0) -> 2.6193792
B31: Capital Turnover | C31: =IFERROR(HistoricaIFS!C5/SUM(HistoricaIFS!C47:C48),0) -> 3.4583567 | D31: =IFERROR(HistoricaIFS!D5/SUM(HistoricaIFS!D47:D48),0) -> 4.6449144 | E31: =IFERROR(HistoricaIFS!E5/SUM(HistoricaIFS!E47:E48),0) -> 3.0551909 | F31: =IFERROR(HistoricaIFS!F5/SUM(HistoricaIFS!F47:F48),0) -> 5.0172916 | G31: =IFERROR(HistoricaIFS!G5/SUM(HistoricaIFS!G47:G48),0) -> 4.138777 | H31: =IFERROR(HistoricaIFS!H5/SUM(HistoricaIFS!H47:H48),0) -> 4.5214404 | I31: =IFERROR(HistoricaIFS!I5/SUM(HistoricaIFS!I47:I48),0) -> 6.2487853 | J31: =IFERROR(HistoricaIFS!J5/SUM(HistoricaIFS!J47:J48),0) -> 7.6335681 | ... L31: =IFERROR(HistoricaIFS!L5/SUM(HistoricaIFS!L47:L48),0) -> 3.7857746 | N31: =IFERROR(AVERAGE(D31:L31),0) -> 4.9063048 | O31: =IFERROR(MEDIAN(D31:L31),0) -> 4.6449144
B33: Debtors Days | C33: =IFERROR(365/C27,0) -> 18.141227 | D33: =IFERROR(365/D27,0) -> 19.049753 | E33: =IFERROR(365/E27,0) -> 24.904965 | F33: =IFERROR(365/F27,0) -> 22.963631 | G33: =IFERROR(365/G27,0) -> 15.620575 | H33: =IFERROR(365/H27,0) -> 18.526667 | I33: =IFERROR(365/I27,0) -> 16.309265 | J33: =IFERROR(365/J27,0) -> 16.603779 | ... L33: =IFERROR(365/L27,0) -> 10.997441 | N33: =IFERROR(AVERAGE(D33:L33),0) -> 17.692491 | O33: =IFERROR(MEDIAN(D33:L33),0) -> 16.603779
B34: Payable Days | C34: =IFERROR(365/C28,0) -> 153.55746 | D34: =IFERROR(365/D28,0) -> 183.94574 | E34: =IFERROR(365/E28,0) -> 178.79203 | F34: =IFERROR(365/F28,0) -> 168.45236 | G34: =IFERROR(365/G28,0) -> 184.98755 | H34: =IFERROR(365/H28,0) -> 210.69421 | I34: =IFERROR(365/I28,0) -> 180.95902 | J34: =IFERROR(365/J28,0) -> 163.77953 | ... L34: =IFERROR(365/L28,0) -> 157.13275 | N34: =IFERROR(AVERAGE(D34:L34),0) -> 175.32025 | O34: =IFERROR(MEDIAN(D34:L34),0) -> 178.79203
B35: Inventory Days | C35: =IFERROR(365/C29,0) -> 43.6533 | D35: =IFERROR(365/D29,0) -> 47.484219 | E35: =IFERROR(365/E29,0) -> 52.753249 | F35: =IFERROR(365/F29,0) -> 47.161976 | G35: =IFERROR(365/G29,0) -> 52.368589 | H35: =IFERROR(365/H29,0) -> 52.732635 | I35: =IFERROR(365/I29,0) -> 46.193417 | J35: =IFERROR(365/J29,0) -> 42.997507 | ... L35: =IFERROR(365/L29,0) -> 39.238984 | N35: =IFERROR(AVERAGE(D35:L35),0) -> 46.791051 | O35: =IFERROR(MEDIAN(D35:L35),0) -> 47.161976
B36: Cash Conversion Cycle | C36: =C34-SUM(C33,C35) -> 91.762933 | D36: =D34-SUM(D33,D35) -> 117.41177 | E36: =E34-SUM(E33,E35) -> 101.13382 | F36: =F34-SUM(F33,F35) -> 98.326751 | G36: =G34-SUM(G33,G35) -> 116.99839 | H36: =H34-SUM(H33,H35) -> 139.4349 | I36: =I34-SUM(I33,I35) -> 118.45634 | J36: =J34-SUM(J33,J35) -> 104.17824 | ... L36: =L34-SUM(L33,L35) -> 106.89633 | N36: =IFERROR(AVERAGE(D36:L36),0) -> 110.83671 | O36: =IFERROR(MEDIAN(D36:L36),0) -> 106.89633
B38: CFO/ Sales | C38: =IFERROR(HistoricaIFS!C81/HistoricaIFS!C5,0) -> 0.13880099 | D38: =IFERROR(HistoricaIFS!D81/HistoricaIFS!D5,0) -> 0.11197567 | E38: =IFERROR(HistoricaIFS!E81/HistoricaIFS!E5,0) -> 0.081828025 | F38: =IFERROR(HistoricaIFS!F81/HistoricaIFS!F5,0) -> 0.062565742 | G38: =IFERROR(HistoricaIFS!G81/HistoricaIFS!G5,0) -> 0.10201175 | H38: =IFERROR(HistoricaIFS!H81/HistoricaIFS!H5,0) -> 0.11609531 | I38: =IFERROR(HistoricaIFS!I81/HistoricaIFS!I5,0) -> 0.051294 | J38: =IFERROR(HistoricaIFS!J81/HistoricaIFS!J5,0) -> 0.10228722 | ... L38: =IFERROR(HistoricaIFS!L81/HistoricaIFS!L5,0) -> 0.14351312 | N38: =IFERROR(AVERAGE(D38:L38),0) -> 0.10311681 | O38: =IFERROR(MEDIAN(D38:L38),0) -> 0.10228722
B39: CFO/Total Asset | C39: =IFERROR(HistoricaIFS!C81/HistoricaIFS!C66,0) -> 0.14400185 | D39: =IFERROR(HistoricaIFS!D81/HistoricaIFS!D66,0) -> 0.11078935 | E39: =IFERROR(HistoricaIFS!E81/HistoricaIFS!E66,0) -> 0.072914417 | F39: =IFERROR(HistoricaIFS!F81/HistoricaIFS!F66,0) -> 0.061795173 | G39: =IFERROR(HistoricaIFS!G81/HistoricaIFS!G66,0) -> 0.083178371 | H39: =IFERROR(HistoricaIFS!H81/HistoricaIFS!H66,0) -> 0.084902092 | I39: =IFERROR(HistoricaIFS!I81/HistoricaIFS!I66,0) -> 0.043405261 | J39: =IFERROR(HistoricaIFS!J81/HistoricaIFS!J66,0) -> 0.10573858 | ... L39: =IFERROR(HistoricaIFS!L81/HistoricaIFS!L66,0) -> 0.1673913 | N39: =IFERROR(AVERAGE(D39:L39),0) -> 0.10154517 | O39: =IFERROR(MEDIAN(D39:L39),0) -> 0.084902092
B40: CFO/Total Debt | C40: =IFERROR(HistoricaIFS!C81/HistoricaIFS!C49,0) -> 0.54641035 | D40: =IFERROR(HistoricaIFS!D81/HistoricaIFS!D49,0) -> 0.38419174 | E40: =IFERROR(HistoricaIFS!E81/HistoricaIFS!E49,0) -> 0.26820544 | F40: =IFERROR(HistoricaIFS!F81/HistoricaIFS!F49,0) -> 0.17792267 | G40: =IFERROR(HistoricaIFS!G81/HistoricaIFS!G49,0) -> 0.21341857 | H40: =IFERROR(HistoricaIFS!H81/HistoricaIFS!H49,0) -> 0.20403774 | I40: =IFERROR(HistoricaIFS!I81/HistoricaIFS!I49,0) -> 0.097528813 | J40: =IFERROR(HistoricaIFS!J81/HistoricaIFS!J49,0) -> 0.26386617 | ... L40: =IFERROR(HistoricaIFS!L81/HistoricaIFS!L49,0) -> 0.882052 | N40: =IFERROR(AVERAGE(D40:L40),0) -> 0.3471534 | O40: =IFERROR(MEDIAN(D40:L40),0) -> 0.26386617

Sheet Cash Flow Data
C3: 42430 | D3: 42795 | E3: 43160 | F3: 43525 | G3: 43891 | H3: 44256 | I3: 44621 | J3: 44986 | K3: 45352 | L3: 45717
B4: Cash from Operating Activity - | C4: 37900 | D4: 30199 | E4: 23857 | F4: 18891 | G4: 26633 | H4: 29001 | I4: 14283 | J4: 35388 | K4: 67915 | L4: 63102
B5: Profit from operations | C5: 38626 | D5: 28840 | E5: 33312 | F5: 28771 | G5: 23352 | H5: 31198 | I5: 26943 | J5: 41694 | K5: 65106 | L5: 58937
B6: Receivables | C6: -2223 | D6: -4152 | E6: -10688 | F6: -9109 | G6: 9950 | H6: -5505 | I6: 185 | J6: -2213 | K6: -1876 | L6: 3573
B7: Inventory | C7: -5743 | D7: -6621 | E7: -3560 | F7: 2069 | G7: 2326 | H7: 3814 | I7: 472 | J7: -5665 | K7: -7265 | L7: 2127
B8: Payables | C8: 3947 | D8: 9301 | E8: 7320 | F8: -4692 | G8: -8085 | H8: 5748 | I8: -7012 | J8: 6945 | K8: 13706 | L8: 1303 | N8: =SUM(C5:C12) -> 39212
B9: Loans Advances | C9: -520 | D9: 0 | E9: 0 | F9: 0 | G9: 0 | H9: 0 | I9: 0 | J9: 0 | K9: 0 | L9: 0
B10: Other WC items | C10: 5852 | D10: 4727 | E10: 494 | F10: 4512 | G10: 875 | H10: -4150 | I10: -4396 | J10: -2194 | K10: 2760 | L10: 1153
B11: Working capital changes | C11: 1313 | D11: 3254 | E11: -6434 | F11: -7221 | G11: 5065 | H11: -93 | I11: -10750 | J11: -3127 | K11: 7325 | L11: 8156
B12: Direct taxes | C12: -2040 | D12: -1895 | E12: -3021 | F12: -2659 | G12: -1785 | H12: -2105 | I12: -1910 | J12: -3179 | K12: -4516 | L12: -3991
B13: Cash from Investing Activity - | C13: -36694 | D13: -39571 | E13: -25139 | F13: -20878 | G13: -33115 | H13: -25672 | I13: -4444 | J13: -15417 | K13: -22781 | L13: -49982
B14: Fixed assets purchased | C14: -31503 | D14: -16072 | E14: -35079 | F14: -35304 | G14: -29702 | H14: -20205 | I14: -15168 | J14: -19230 | K14: -31414 | L14: -38042
B15: Fixed assets sold | C15: 59 | D15: 53 | E15: 30 | F15: 67 | G15: 171 | H15: 351 | I15: 230 | J15: 285 | K15: 231 | L15: 974
B16: Investments purchased | C16: -4728 | D16: -6 | E16: -329 | F16: -130 | G16: -1439 | H16: -7530 | I16: -3008 | J16: -50 | K16: -74 | L16: -12677
B17: Investments sold | C17: 89 | D17: 1965 | E17: 2381 | F17: 5644 | G17: 21 | H17: 226 | I17: 104 | J17: 6895 | K17: 10821 | L17: 111
B18: Interest received | C18: 731 | D18: 638 | E18: 690 | F18: 761 | G18: 1104 | H18: 428 | I18: 653 | J18: 973 | K18: 2493 | L18: 2420
B19: Dividends received | C19: 58 | D19: 620 | E19: 1797 | F19: 232 | G19: 21 | H19: 18 | I19: 32 | J19: 46 | K19: 47 | L19: 64
B20: Investment in group cos | C20: 0 | D20: -107 | E20: -4 | F20: -9 | G20: -606 | H20: -10 | I20: 0 | J20: 0 | K20: -150 | L20: 0
... B34: Net Cash Flow | C34: -2589 | D34: -3167 | E34: 730 | F34: 6843 | G34: -3092 | H34: 13232 | I34: 6459 | J34: -6272 | K34: 8128 | L34: -5666

Sheet Financials>

Sheet Rm 
B3: Return On Market
B5: Year | C5: Annual
B6: 2000 | C6: -14.65 | E6: Average Return | G6: =(AVERAGE(C6:C30))/100 -> 0.153348
B7: 2001 | C7: -16.18 | E7: Dividend yeild | G7: 1.24% 1
B8: 2002 | C8: 3.25 | E8: Total return | G8: =SUM(G6:G7) -> 0.153348
B9: 2003 | C9: 71.9
B10: 2004 | C10: 10.68
B11: 2005 | C11: 36.34
B12: 2006 | C12: 39.83
B13: 2007 | C13: 54.77
B14: 2008 | C14: -51.79
B15: 2009 | C15: 75.76
B16: 2010 | C16: 17.95
B17: 2011 | C17: -24.62
B18: 2012 | C18: 27.7
B19: 2013 | C19: 6.76
B20: 2014 | C20: 31.39
... B30: 2024 | C30: 8.75

Sheet Raw FS
B2: Particulars | C2: 41699 | D2: 42064 | E2: 42430 | F2: 42795 | G2: 43160 | H2: 43525 | I2: 43891 | J2: 44256 | K2: 44621 | L2: 44986 | M2: 45352 | N2: 45717
B4: Equity Capital | C4: 96 | D4: 96 | E4: 96 | F4: 96 | G4: 96 | H4: 96 | I4: 96 | J4: 96 | K4: 96 | L4: 96 | M4: 96 | N4: 96
B5: Reserves | C5: 3943 | D5: 4646 | E5: 6429 | F5: 7508 | G5: 8314 | H5: 9375 | I5: 10034 | J5: 12710 | K5: 13716 | L5: 15896 | M5: 18632 | N5: 19304
B6: Borrowings -
B7: Long term Borrowings | C7: 41 | D7: 78 | E7: 73 | F7: 41 | G7: 28 | H7: 19 | I7: 19 | J7: 15 | K7: 45 | L7: 76 | M7: 54 | N7: 260
B8: Short term Borrowings | C8: 199 | D8: 332 | E8: 231 | F8: 504 | G8: 492 | H8: 597 | I8: 321 | J8: 334 | K8: 731 | L8: 896 | M8: 1053 | N8: 604
B9: Lease Liabilities | C9: 0 | D9: 0 | E9: 0 | F9: 0 | G9: 0 | H9: 693 | I9: 764 | J9: 745 | K9: 811 | L9: 960 | M9: 1367 | N9: 1427
B10: Other Borrowings | C10: 9 | D10: 8 | E10: 20 | F10: 15 | G10: 13 | H10: 11 | I10: 15 | J10: 0 | K10: 0 | L10: 0 | M10: 0 | N10: 0
B11: Other Liabilities -
B12: Non controlling int | C12: 246 | D12: 264 | E12: 384 | F12: 375 | G12: 328 | H12: 361 | I12: 404 | J12: 423 | K12: 388 | L12: 454 | M12: 695 | N12: 659
B13: Trade Payables | C13: 1746 | D13: 1549 | E13: 1565 | F13: 1923 | G13: 2160 | H13: 2394 | I13: 2137 | J13: 3379 | K13: 4164 | L13: 3635 | M13: 3831 | N13: 3848
B14: Advance from Customers | C14: 0 | D14: 5 | E14: 12 | F14: 17 | G14: 16 | H14: 13 | I14: 29 | J14: 41 | K14: 76 | L14: 108 | M14: 154 | N14: 173
B15: Other liability items | C15: 1795 | D15: 1937 | E15: 1750 | F15: 1925 | G15: 2316 | H15: 2690 | I15: 2320 | J15: 2613 | K15: 2932 | L15: 3657 | M15: 4017 | N15: 3985
B16: Total Liabilities | C16: 8075 | D16: 8914 | E16: 10559 | F16: 12405 | G16: 13763 | H16: 16249 | I16: 16138 | J16: 20355 | K16: 22958 | L16: 25779 | M16: 29901 | N16: 30355
B18: Fixed Assets - | C18: 2562 | D18: 2660 | E18: 3416 | F18: 3304 | G18: 3732 | H18: 6497 | I18: 6272 | J18: 5859 | K18: 5519 | L18: 5770 | M18: 7147 | N18: 9220
B19: Land | C19: 247 | D19: 251 | E19: 429 | F19: 408 | G19: 586 | H19: 605 | I19: 640 | J19: 644 | K19: 644 | L19: 804 | M19: 1126 | N19: 1050
B20: Building | C20: 931 | D20: 962 | E20: 923 | F20: 931 | G20: 957 | H20: 2402 | I20: 2257 | J20: 2249 | K20: 2325 | L20: 2883 | M20: 3390 | N20: 4136
B21: Plant Machinery | C21: 2054 | D21: 2132 | E21: 1793 | F21: 1980 | G21: 2157 | H21: 4006 | I21: 4208 | J21: 4340 | K21: 4531 | L21: 4825 | M21: 5422 | N21: 7576
B22: Equipments | C22: 155 | D22: 171 | E22: 97 | F22: 119 | G22: 200 | H22: 221 | I22: 241 | J22: 243 | K22: 253 | L22: 270 | M22: 298 | N22: 325
B23: Furniture n fittings | C23: 71 | D23: 83 | E23: 49 | F23: 59 | G23: 72 | H23: 88 | I23: 94 | J23: 99 | K23: 113 | L23: 146 | M23: 175 | N23: 203
B24: Vehicles | C24: 14 | D24: 18 | E24: 11 | F24: 14 | G24: 27 | H24: 47 | I24: 43 | J24: 38 | K24: 32 | L24: 36 | M24: 40 | N24: 39
... B40: Total Assets | C40: 8075 | D40: 8914 | E40: 10559 | F40: 12405 | G40: 13763 | H40: 16249 | I40: 16138 | J40: 20355 | K40: 22958 | L40: 25779 | M40: 29901 | N40: 30355

Sheet Intresnsic Growth
B2: Calculation Of ROIC | E2: 44256 | F2: 44621 | G2: 44986 | H2: 45352 | I2: 45717
B4: ='Raw FS'!B32 -> Inventories | E4: ='Raw FS'!J32 -> 3799 | F4: ='Raw FS'!K32 -> 6153 | G4: ='Raw FS'!L32 -> 6211 | H4: ='Raw FS'!M32 -> 5923 | I4: ='Raw FS'!N32 -> 6719
B5: ='Raw FS'!B33 -> Trade receivables - | E5: ='Raw FS'!J33 -> 2602 | F5: ='Raw FS'!K33 -> 3871 | G5: ='Raw FS'!L33 -> 4637 | H5: ='Raw FS'!M33 -> 4889 | I5: ='Raw FS'!N33 -> 4314
B6: ='Raw FS'!B38 -> Loans n Advances | E6: ='Raw FS'!J38 -> 11 | F6: ='Raw FS'!K38 -> 8 | G6: ='Raw FS'!L38 -> 12 | H6: ='Raw FS'!M38 -> 17 | I6: ='Raw FS'!N38 -> 22
B7: ='Raw FS'!B39 -> Other asset items | E7: ='Raw FS'!J39 -> 2555 | F7: ='Raw FS'!K39 -> 2869 | G7: ='Raw FS'!L39 -> 3024 | H7: ='Raw FS'!M39 -> 3555 | I7: ='Raw FS'!N39 -> 3319
B8: Total Current asset | E8: =SUM(E4:E7) -> 8967 | F8: =SUM(F4:F7) -> 12901 | G8: =SUM(G4:G7) -> 13884 | H8: =SUM(H4:H7) -> 14384 | I8: =SUM(I4:I7) -> 14374
B10: Current Liablities
B11: ='Raw FS'!B13 -> Trade Payables | E11: ='Raw FS'!J13 -> 3379 | F11: ='Raw FS'!K13 -> 4164 | G11: ='Raw FS'!L13 -> 3635 | H11: ='Raw FS'!M13 -> 3831 | I11: ='Raw FS'!N13 -> 3848
B12: ='Raw FS'!B14 -> Advance from Customers | E12: ='Raw FS'!J14 -> 41 | F12: ='Raw FS'!K14 -> 76 | G12: ='Raw FS'!L14 -> 108 | H12: ='Raw FS'!M14 -> 154 | I12: ='Raw FS'!N14 -> 173
B13: ='Raw FS'!B15 -> Other liability items | E13: ='Raw FS'!J15 -> 2613 | F13: ='Raw FS'!K15 -> 2932 | G13: ='Raw FS'!L15 -> 3657 | H13: ='Raw FS'!M15 -> 4017 | I13: ='Raw FS'!N15 -> 3985
A14: # | B14: Total Current Liablities | E14: =SUM(E11:E13) -> 6033 | F14: =SUM(F11:F13) -> 7172 | G14: =SUM(G11:G13) -> 7400 | H14: =SUM(H11:H13) -> 8002 | I14: =SUM(I11:I13) -> 8006
A16: # | B16: Net Working Capital | E16: =E8-E14 -> 2934 | F16: =F8-F14 -> 5729 | G16: =G8-G14 -> 6484 | H16: =H8-H14 -> 6382 | I16: =I8-I14 -> 6368
A18: # | B18: Non Current Asset
B19: ='Raw FS'!B19 -> Land | E19: ='Raw FS'!J19 -> 644 | F19: ='Raw FS'!K19 -> 644 | G19: ='Raw FS'!L19 -> 804 | H19: ='Raw FS'!M19 -> 1126 | I19: ='Raw FS'!N19 -> 1050
B20: ='Raw FS'!B20 -> Building | E20: ='Raw FS'!J20 -> 2249 | F20: ='Raw FS'!K20 -> 2325 | G20: ='Raw FS'!L20 -> 2883 | H20: ='Raw FS'!M20 -> 3390 | I20: ='Raw FS'!N20 -> 4136
B21: ='Raw FS'!B21 -> Plant Machinery | E21: ='Raw FS'!J21 -> 4340 | F21: ='Raw FS'!K21 -> 4531 | G21: ='Raw FS'!L21 -> 4825 | H21: ='Raw FS'!M21 -> 5422 | I21: ='Raw FS'!N21 -> 7576
B22: ='Raw FS'!B22 -> Equipments | E22: ='Raw FS'!J22 -> 243 | F22: ='Raw FS'!K22 -> 253 | G22: ='Raw FS'!L22 -> 270 | H22: ='Raw FS'!M22 -> 298 | I22: ='Raw FS'!N22 -> 325
B23: ='Raw FS'!B23 -> Furniture n fittings | E23: ='Raw FS'!J23 -> 99 | F23: ='Raw FS'!K23 -> 113 | G23: ='Raw FS'!L23 -> 146 | H23: ='Raw FS'!M23 -> 175 | I23: ='Raw FS'!N23 -> 203
B24: ='Raw FS'!B24 -> Vehicles | E24: ='Raw FS'!J24 -> 38 | F24: ='Raw FS'!K24 -> 32 | G24: ='Raw FS'!L24 -> 36 | H24: ='Raw FS'!M24 -> 40 | I24: ='Raw FS'!N24 -> 39
B25: ='Raw FS'!B25 -> Intangible Assets | E25: ='Raw FS'!J25 -> 476 | F25: ='Raw FS'!K25 -> 345 | G25: ='Raw FS'!L25 -> 422 | H25: ='Raw FS'!M25 -> 850 | I25: ='Raw FS'!N25 -> 827
B26: ='Raw FS'!B26 -> Other fixed assets | E26: ='Raw FS'!J26 -> 302 | F26: ='Raw FS'!K26 -> 294 | G26: ='Raw FS'!L26 -> 289 | H26: ='Raw FS'!M26 -> 321 | I26: ='Raw FS'!N26 -> 328
B27: Gross Block | E27: =SUM(E19:E26) -> 8391 | F27: =SUM(F19:F26) -> 8537 | G27: =SUM(G19:G26) -> 9675 | H27: =SUM(H19:H26) -> 11622 | I27: =SUM(I19:I26) -> 14484
B28: ='Raw FS'!B28 -> Accumulated Depreciation | E28: ='Raw FS'!J28 -> 2533 | F28: ='Raw FS'!K28 -> 3019 | G28: ='Raw FS'!L28 -> 3814 | H28: ='Raw FS'!M28 -> 4381 | I28: ='Raw FS'!N28 -> 4945
A29: # | B29: Net Non Current Asset | E29: =E27-E28 -> 5858 | F29: =F27-F28 -> 5518 | G29: =G27-G28 -> 5861 | H29: =H27-H28 -> 7241 | I29: =I27-I28 -> 9539
A31: # | B31: Invested Capital | E31: =E29+E16 -> 8792 | F31: =F29+F16 -> 11247 | G31: =G29+G16 -> 12345 | H31: =H29+H16 -> 13623 | I31: =I29+I16 -> 15907
B32: EBIT | E32: =HistoricaIFS!H26+HistoricaIFS!H20 -> 8740.72 | F32: =HistoricaIFS!I26+HistoricaIFS!I20 -> -115.6 | G32: =HistoricaIFS!J26+HistoricaIFS!J20 -> 6955.44 | H32: =HistoricaIFS!K26+HistoricaIFS!K20 -> 30585 | I32: =HistoricaIFS!L26+HistoricaIFS!L20 -> 31960
A34: # | B34: ROIC | E34: =E32/E31 -> 0.99416742 | F34: =F32/F31 -> -0.010278296 | G34: =G32/G31 -> 0.56342163 | H34: =H32/H31 -> 2.2451002 | I34: =I32/I31 -> 2.0091783
B36: Calculation Of Reinvestment Rate | E36: =E2 -> 44256 | F36: =F2 -> 44621 | G36: =G2 -> 44986 | H36: =H2 -> 45352 | I36: =I2 -> 45717
B38: Net capax | E38: =-SUM('Cash Flow Data'!H14:H15) -> 19854 | F38: =-SUM('Cash Flow Data'!I14:I15) -> 14938 | G38: =-SUM('Cash Flow Data'!J14:J15) -> 18945 | H38: =-SUM('Cash Flow Data'!K14:K15) -> 31183 | I38: =-SUM('Cash Flow Data'!L14:L15) -> 37068
B39: Change In Working Capital | F39: =F16-E16 -> 2795 | G39: =G16-F16 -> 755 | H39: =H16-G16 -> -102 | I39: =I16-H16 -> -14
B41: EBIT | E41: =E32 -> 8740.72 | F41: =F32 -> -115.6 | G41: =G32 -> 6955.44 | H41: =H32 -> 30585 | I41: =I32 -> 31960
B42: Marginal Tax Rate | E42: 0.25 | F42: 0.25 | G42: 0.25 | H42: 0.25 | I42: 0.25
B43: EBIT(1-T) | E43: =E41*(1-E42) -> 6555.54 | F43: =F41*(1-F42) -> -86.7 | G43: =G41*(1-G42) -> 5216.58 | H43: =H41*(1-H42) -> 22938.75 | I43: =I41*(1-I42) -> 23970
B45: Reinvestment | F45: =SUM(F38:F39) -> 17733 | G45: =SUM(G38:G39) -> 19700 | H45: =SUM(H38:H39) -> 31081 | I45: =SUM(I38:I39) -> 37054
B46: Reinstemnt Rate | F46: =F45/F43 -> -204.53287 | G46: =G45/G43 -> 3.7764206 | H46: =H45/H43 -> 1.3549561 | I46: =I45/I43 -> 1.545849
H48: 4 Year Average | I48: =AVERAGE(F46:I46) -> -49.463912
H49: 4 Year Median | I49: =MEDIAN(F46:I46) -> 1.4504026
B52: Calculation Of Growth Rate | E52: =E36 -> 44256 | F52: =F36 -> 44621 | G52: =G36 -> 44986 | H52: =H36 -> 45352 | I52: =I36 -> 45717
B54: Reinstemnt Rate | F54: =F46 -> -204.53287 | G54: =G46 -> 3.7764206 | H54: =H46 -> 1.3549561 | I54: =I46 -> 1.545849
B55: =B34 -> ROIC | F55: =F34 -> -0.010278296 | G55: =G34 -> 0.56342163 | H55: =H34 -> 2.2451002 | I55: =I34 -> 2.0091783
B57: Intrensic Growth | F57: =F54*F55 -> 2.1022495 | G57: =G54*G55 -> 2.127717 | H57: =H54*H55 -> 3.0420123 | I57: =I54*I55 -> 3.1058863
